{
  "data": [
    {
      "token": "0xfaba6f8e4a5e8ab82f62fe7c39859fa577269be3",
      "chain": "eth",
      "symbol": "ONDO",
      "name": "Ondo",
      "logo_url": "https://www.iconaves.com/token_icon/eth/0xfaba6f8e4a5e8ab82f62fe7c39859fa577269be3.png",
      "current_price_usd": 1.09555848732134,
      "price_change_24h": 8.38,
      "tx_volume_u_24h": 6528080.921078023,
      "holders": 135536,
      "market_cap": "10955584873.21340000000000",
      "fdv": "10955584873.21340000000000",
      "risk_score": "40"
    },
    {
      "token": "0x0c880f6761f1af8d9aa9c466984b80dab9a8c9e8",
      "chain": "arbitrum",
      "symbol": "PENDLE",
      "name": "PENDLE",
      "logo_url": "https://www.iconaves.com/token_icon/arbitrum/0x0c880f6761f1af8d9aa9c466984b80dab9a8c9e8.png",
      "current_price_usd": 4.077268350198192,
      "price_change_24h": 5.75,
      "tx_volume_u_24h": 2541931.253588,
      "holders": 57668,
      "market_cap": "122410712.498793613598751181077812330721456",
      "fdv": "122410712.498793613598751181077812330721456",
      "risk_score": "55"
    },
    {
      "token": "0x9f8f72aa9304c8b593d555f12ef6589cc3a579a2",
      "chain": "eth",
      "symbol": "MKR",
      "name": "MKR",
      "logo_url": "https://www.iconaves.com/token_icon/eth/0x9f8f72aa9304c8b593d555f12ef6589cc3a579a2.png",
      "current_price_usd": 1894.9016241649922,
      "price_change_24h": 8.94,
      "tx_volume_u_24h": 2469094.425006,
      "holders": 101623,
      "market_cap": "1625062081.65414073251163620172202",
      "fdv": "1625062081.65414073251163620172202",
      "risk_score": "55"
    },
    {
      "token": "0x4507cef57c46789ef8d1a19ea45f4216bae2b528",
      "chain": "bsc",
      "symbol": "TOKEN",
      "name": "TokenFi",
      "logo_url": "https://www.iconaves.com/token_icon/bsc/0x4507cef57c46789ef8d1a19ea45f4216bae2b528.png",
      "current_price_usd": 0.025760466002692023,
      "price_change_24h": 15,
      "tx_volume_u_24h": 1469006.624038,
      "holders": 51244,
      "market_cap": "125843680.3221358790962267530507501480",
      "fdv": "125843680.3221358790962267530507501480",
      "risk_score": "20"
    },
    {
      "token": "0x3593d125a4f7849a1b059e64f4517a86dd60c95d",
      "chain": "eth",
      "symbol": "OM",
      "name": "MANTRA DAO",
      "logo_url": "https://www.iconaves.com/token_icon/eth/0x3593d125a4f7849a1b059e64f4517a86dd60c95d.png",
      "current_price_usd": 0.4622940686205955,
      "price_change_24h": 20.81,
      "tx_volume_u_24h": 1034841.765748,
      "holders": 42626,
      "market_cap": "362945992.257498404293709972476280",
      "fdv": "362945992.257498404293709972476280",
      "risk_score": "55"
    },
    {
      "token": "0x808507121b80c02388fad14726482e061b8da827",
      "chain": "eth",
      "symbol": "PENDLE",
      "name": "PENDLE",
      "logo_url": "https://www.iconaves.com/token_icon/eth/0x808507121b80c02388fad14726482e061b8da827.png",
      "current_price_usd": 4.107704504603337,
      "price_change_24h": 6.58,
      "tx_volume_u_24h": 948045.2660684737,
      "holders": 53851,
      "market_cap": "1156431568.20259337948423074341528",
      "fdv": "1156431568.20259337948423074341528",
      "risk_score": "55"
    },
    {
      "token": "0x9ce84f6a69986a83d92c324df10bc8e64771030f",
      "chain": "eth",
      "symbol": "CHEX",
      "name": "CHEX",
      "logo_url": "https://www.iconaves.com/token_icon/eth/0x9ce84f6a69986a83d92c324df10bc8e64771030f.png",
      "current_price_usd": 0.25256234175225295,
      "price_change_24h": 6.14,
      "tx_volume_u_24h": 879124.259313,
      "holders": 9450,
      "market_cap": "148453179.232669674212069793800095",
      "fdv": "148453179.232669674212069793800095",
      "risk_score": "70"
    },
    {
      "token": "0x320623b8e4ff03373931769a31fc52a4e78b5d70",
      "chain": "eth",
      "symbol": "RSR",
      "name": "RSR",
      "logo_url": "https://www.iconaves.com/token_icon/eth/0x320623b8e4ff03373931769a31fc52a4e78b5d70.png",
      "current_price_usd": 0.010568248589099903,
      "price_change_24h": 2.18,
      "tx_volume_u_24h": 408745.63723066606,
      "holders": 31905,
      "market_cap": "1056824858.909990300000000000",
      "fdv": "1056824858.909990300000000000",
      "risk_score": "55"
    },
    {
      "token": "6dKCoWjpj5MFU5gWDEFdpUUeBasBLK3wLEwhUzQPAa1e",
      "chain": "solana",
      "symbol": "CHEX",
      "name": "CHEX",
      "logo_url": "https://www.iconaves.com/token_icon/solana/6dKCoWjpj5MFU5gWDEFdpUUeBasBLK3wLEwhUzQPAa1e.png",
      "current_price_usd": 0.2498468738811139,
      "price_change_24h": 5.77,
      "tx_volume_u_24h": 380938.350774,
      "holders": 11594,
      "market_cap": "28241973.09110808526984359663448",
      "fdv": "28241973.09110808526984359663448",
      "risk_score": "80"
    },
    {
      "token": "0x4507cef57c46789ef8d1a19ea45f4216bae2b528",
      "chain": "eth",
      "symbol": "TOKEN",
      "name": "TokenFi",
      "logo_url": "https://www.iconaves.com/token_icon/eth/0x4507cef57c46789ef8d1a19ea45f4216bae2b528.png",
      "current_price_usd": 0.025786128480214422,
      "price_change_24h": 16.04,
      "tx_volume_u_24h": 367793.296569,
      "holders": 31245,
      "market_cap": "128930642.401072110000000000",
      "fdv": "128930642.401072110000000000",
      "risk_score": "20"
    },
    {
      "token": "ATRLuHph8dxnPny4WSNW7fxkhbeivBrtWbY6BfB4xpLj",
      "chain": "solana",
      "symbol": "ATR",
      "name": "ATR",
      "logo_url": "https://www.iconaves.com/token_icon/solana/ATRLuHph8dxnPny4WSNW7fxkhbeivBrtWbY6BfB4xpLj.png",
      "current_price_usd": 0.026310769416062967,
      "price_change_24h": 0.12,
      "tx_volume_u_24h": 244119.69023,
      "holders": 12451,
      "market_cap": "33250531.762045286787738166949846193",
      "fdv": "33250531.762045286787738166949846193",
      "risk_score": "55"
    },
    {
      "token": "0x66761fa41377003622aee3c7675fc7b5c1c2fac5",
      "chain": "eth",
      "symbol": "CPOOL",
      "name": "CPOOL",
      "logo_url": "https://www.iconaves.com/token_icon/eth/0x66761fa41377003622aee3c7675fc7b5c1c2fac5.png",
      "current_price_usd": 0.18021447368836818,
      "price_change_24h": 10.42,
      "tx_volume_u_24h": 219887.470245,
      "holders": 20844,
      "market_cap": "180214473.68836818000000000",
      "fdv": "180214473.68836818000000000",
      "risk_score": "40"
    },
    {
      "token": "0x0a638f07acc6969abf392bb009f216d22adea36d",
      "chain": "eth",
      "symbol": "BKN",
      "name": "BKN",
      "logo_url": "https://www.iconaves.com/token_icon/eth/0x0a638f07acc6969abf392bb009f216d22adea36d.png",
      "current_price_usd": 0.29618800324425976,
      "price_change_24h": 28.04,
      "tx_volume_u_24h": 215581.074529,
      "holders": 3291,
      "market_cap": "42354884.46392914568000000",
      "fdv": "42354884.46392914568000000",
      "risk_score": "66"
    },
    {
      "token": "0xdab396ccf3d84cf2d07c4454e10c8a6f5b008d2b",
      "chain": "eth",
      "symbol": "GFI",
      "name": "GFI",
      "logo_url": "https://www.iconaves.com/token_icon/eth/0xdab396ccf3d84cf2d07c4454e10c8a6f5b008d2b.png",
      "current_price_usd": 1.0025990990659432,
      "price_change_24h": 7.94,
      "tx_volume_u_24h": 196483.7579081807,
      "holders": 15208,
      "market_cap": "114582753.8925080516954448",
      "fdv": "114582753.8925080516954448",
      "risk_score": "55"
    },
    {
      "token": "0xb3ed0a426155b79b898849803e3b36552f7ed507",
      "chain": "bsc",
      "symbol": "PENDLE",
      "name": "PENDLE",
      "logo_url": "https://www.iconaves.com/token_icon/bsc/0xb3ed0a426155b79b898849803e3b36552f7ed507.png",
      "current_price_usd": 4.088870819933244,
      "price_change_24h": 6.24,
      "tx_volume_u_24h": 129193.48282058943,
      "holders": 13440,
      "market_cap": "13380265.6292630506629243185057052",
      "fdv": "13380265.6292630506629243185057052",
      "risk_score": "100"
    },
    {
      "token": "0x73d7c860998ca3c01ce8c808f5577d94d545d1b4",
      "chain": "eth",
      "symbol": "IXS",
      "name": "IXS",
      "logo_url": "https://www.iconaves.com/token_icon/eth/0x73d7c860998ca3c01ce8c808f5577d94d545d1b4.png",
      "current_price_usd": 0.23732253586918373,
      "price_change_24h": 3.89,
      "tx_volume_u_24h": 84309.86902467012,
      "holders": 7525,
      "market_cap": "42718056.45645307140000000",
      "fdv": "42718056.45645307140000000",
      "risk_score": "55"
    },
    {
      "token": "0xaa7a9ca87d3694b5755f213b5d04094b8d0f0a6f",
      "chain": "eth",
      "symbol": "TRAC",
      "name": "TRAC",
      "logo_url": "https://www.iconaves.com/token_icon/eth/0xaa7a9ca87d3694b5755f213b5d04094b8d0f0a6f.png",
      "current_price_usd": 0.4834443233744915,
      "price_change_24h": 2.34,
      "tx_volume_u_24h": 78644.34844133587,
      "holders": 1,
      "market_cap": "241722161.6872457500000000",
      "fdv": "241722161.6872457500000000",
      "risk_score": "50"
    },
    {
      "token": "0x80d55c03180349fff4a229102f62328220a96444",
      "chain": "eth",
      "symbol": "OPUL",
      "name": "Opulous",
      "logo_url": "https://www.iconaves.com/token_icon/eth/0x80d55c03180349fff4a229102f62328220a96444.png",
      "current_price_usd": 0.04028158666902771,
      "price_change_24h": 30.5,
      "tx_volume_u_24h": 62423.99038630016,
      "holders": 5396,
      "market_cap": "20140793.33451385500000000",
      "fdv": "20140793.33451385500000000",
      "risk_score": "66"
    },
    {
      "token": "0x9ff58067bd8d239000010c154c6983a325df138e",
      "chain": "eth",
      "symbol": "PROPC",
      "name": "PROPC",
      "logo_url": "https://www.iconaves.com/token_icon/eth/0x9ff58067bd8d239000010c154c6983a325df138e.png",
      "current_price_usd": 0.6597209593314838,
      "price_change_24h": 9.75,
      "tx_volume_u_24h": 61627.1987436509,
      "holders": 11589,
      "market_cap": "56022037.3067366158943789197726876",
      "fdv": "56022037.3067366158943789197726876",
      "risk_score": "66"
    },
    {
      "token": "0x4b9278b94a1112cad404048903b8d343a810b07e",
      "chain": "eth",
      "symbol": "HIFI",
      "name": "HIFI",
      "logo_url": "https://www.iconaves.com/token_icon/eth/0x4b9278b94a1112cad404048903b8d343a810b07e.png",
      "current_price_usd": 0.14987506378021342,
      "price_change_24h": -9.16,
      "tx_volume_u_24h": 57261.967457,
      "holders": 2853,
      "market_cap": "25001107.7970989133366372403465284",
      "fdv": "25001107.7970989133366372403465284",
      "risk_score": "40"
    },
    {
      "token": "0x644192291cc835a93d6330b24ea5f5fedd0eef9e",
      "chain": "eth",
      "symbol": "NXRA",
      "name": "NXRA",
      "logo_url": "https://www.iconaves.com/token_icon/eth/0x644192291cc835a93d6330b24ea5f5fedd0eef9e.png",
      "current_price_usd": 0.01653488524075662,
      "price_change_24h": 26.92,
      "tx_volume_u_24h": 40478.938969143805,
      "holders": 20278,
      "market_cap": "18991395.063120149273565302298390",
      "fdv": "18991395.063120149273565302298390",
      "risk_score": "70"
    },
    {
      "token": "0x4f1960e29b2ca581a38c5c474e123f420f8092db",
      "chain": "bsc",
      "symbol": "UBXS",
      "name": "UBXS",
      "logo_url": "https://www.iconaves.com/token_icon/bsc/0x4f1960e29b2ca581a38c5c474e123f420f8092db.png",
      "current_price_usd": 0.012419810279011628,
      "price_change_24h": 6.26,
      "tx_volume_u_24h": 29353.845734231825,
      "holders": 28830,
      "market_cap": "792284.0606557558018600921275120000",
      "fdv": "817222.1647319025784538223182960000",
      "risk_score": "40"
    },
    {
      "token": "0x6123b0049f904d730db3c36a31167d9d4121fa6b",
      "chain": "eth",
      "symbol": "RBN",
      "name": "Ribbon Finance",
      "logo_url": "https://www.iconaves.com/token_icon/eth/0x6123b0049f904d730db3c36a31167d9d4121fa6b.png",
      "current_price_usd": 0.16416035733882609,
      "price_change_24h": 2.44,
      "tx_volume_u_24h": 24782.294306268646,
      "holders": 5499,
      "market_cap": "164160357.33882609000000000",
      "fdv": "164160357.33882609000000000",
      "risk_score": "55"
    },
    {
      "token": "0x509a38b7a1cc0dcd83aa9d06214663d9ec7c7f4a",
      "chain": "eth",
      "symbol": "BST",
      "name": "BST",
      "logo_url": "https://www.iconaves.com/token_icon/eth/0x509a38b7a1cc0dcd83aa9d06214663d9ec7c7f4a.png",
      "current_price_usd": 0.1539353326377066,
      "price_change_24h": 7.59,
      "tx_volume_u_24h": 19049.954493801473,
      "holders": 4631,
      "market_cap": "9145982.4494312737604334676341450",
      "fdv": "9145982.4494312737604334676341450",
      "risk_score": "70"
    },
    {
      "token": "0xebd9d99a3982d547c5bb4db7e3b1f9f14b67eb83",
      "chain": "eth",
      "symbol": "ID",
      "name": "ID",
      "logo_url": "https://www.iconaves.com/token_icon/eth/0xebd9d99a3982d547c5bb4db7e3b1f9f14b67eb83.png",
      "current_price_usd": 0.01843433193373212,
      "price_change_24h": 14.46,
      "tx_volume_u_24h": 17371.620554170855,
      "holders": 6107,
      "market_cap": "14747465.54698569600000000",
      "fdv": "14747465.54698569600000000",
      "risk_score": "40"
    },
    {
      "token": "0x226bb599a12c826476e3a771454697ea52e9e220",
      "chain": "eth",
      "symbol": "PRO",
      "name": "PRO",
      "logo_url": "https://www.iconaves.com/token_icon/eth/0x226bb599a12c826476e3a771454697ea52e9e220.png",
      "current_price_usd": 0.8183668396854221,
      "price_change_24h": 6.58,
      "tx_volume_u_24h": 16775.776301,
      "holders": 20047,
      "market_cap": "81836683.9685422100000000",
      "fdv": "81836683.9685422100000000",
      "risk_score": "40"
    },
    {
      "token": "0xb17548c7b510427baac4e267bea62e800b247173",
      "chain": "eth",
      "symbol": "SMT",
      "name": "SMT",
      "logo_url": "https://www.iconaves.com/token_icon/eth/0xb17548c7b510427baac4e267bea62e800b247173.png",
      "current_price_usd": 0.11106901077078307,
      "price_change_24h": 13.93,
      "tx_volume_u_24h": 16480.193989,
      "holders": 8960,
      "market_cap": "17191149.336835334734965598459007",
      "fdv": "17191149.336835334734965598459007",
      "risk_score": "40"
    },
    {
      "token": "0xc011a73ee8576fb46f5e1c5751ca3b9fe0af2a6f",
      "chain": "eth",
      "symbol": "SNX",
      "name": "Synthetix Network Token",
      "logo_url": "https://www.iconaves.com/token_icon/eth/0xc011a73ee8576fb46f5e1c5751ca3b9fe0af2a6f.png",
      "current_price_usd": 0.9024428777449044,
      "price_change_24h": 12.04,
      "tx_volume_u_24h": 14527.649054,
      "holders": 85866,
      "market_cap": "306731174.43039699783211504524384",
      "fdv": "306731174.43039699783211504524384",
      "risk_score": "55"
    },
    {
      "token": "0x6e5970dbd6fc7eb1f29c6d2edf2bc4c36124c0c1",
      "chain": "eth",
      "symbol": "TRADE",
      "name": "TRADE",
      "logo_url": "https://www.iconaves.com/token_icon/eth/0x6e5970dbd6fc7eb1f29c6d2edf2bc4c36124c0c1.png",
      "current_price_usd": 0.20684533214858952,
      "price_change_24h": 3.06,
      "tx_volume_u_24h": 14366.134542,
      "holders": 4214,
      "market_cap": "20684533.21485895200000000",
      "fdv": "20684533.21485895200000000",
      "risk_score": "70"
    },
    {
      "token": "0xd6fdde76b8c1c45b33790cc8751d5b88984c44ec",
      "chain": "bsc",
      "symbol": "STRX",
      "name": "StrikeX",
      "logo_url": "https://www.iconaves.com/token_icon/bsc/0xd6fdde76b8c1c45b33790cc8751d5b88984c44ec.png",
      "current_price_usd": 0.029452065650447896,
      "price_change_24h": 3.33,
      "tx_volume_u_24h": 13897.647513954958,
      "holders": 14475,
      "market_cap": "25943801.57257706131325891772645688",
      "fdv": "25943801.57257706131325891772645688",
      "risk_score": "40"
    },
    {
      "token": "0x43c73b90e0c2a355784dcf0da12f477729b31e77",
      "chain": "polygon",
      "symbol": "SOIL",
      "name": "SOIL",
      "logo_url": "https://www.iconaves.com/token_icon/polygon/0x43c73b90e0c2a355784dcf0da12f477729b31e77.png",
      "current_price_usd": 0.44953644073245985,
      "price_change_24h": 21.26,
      "tx_volume_u_24h": 13888.852231861882,
      "holders": 4887,
      "market_cap": "44504107.63251352515000000",
      "fdv": "44504107.63251352515000000",
      "risk_score": "55"
    },
    {
      "token": "0x4c19596f5aaff459fa38b0f7ed92f11ae6543784",
      "chain": "eth",
      "symbol": "TRU",
      "name": "TRU",
      "logo_url": "https://www.iconaves.com/token_icon/eth/0x4c19596f5aaff459fa38b0f7ed92f11ae6543784.png",
      "current_price_usd": 0.049498880170221846,
      "price_change_24h": 10.72,
      "tx_volume_u_24h": 13763.529045,
      "holders": 12419,
      "market_cap": "64363981.5461758968794194087310658",
      "fdv": "64363981.5461758968794194087310658",
      "risk_score": "70"
    },
    {
      "token": "0xa73164db271931cf952cbaeff9e8f5817b42fa5c",
      "chain": "bsc",
      "symbol": "LAND",
      "name": "LAND",
      "logo_url": "https://www.iconaves.com/token_icon/bsc/0xa73164db271931cf952cbaeff9e8f5817b42fa5c.png",
      "current_price_usd": 0.6775638620639711,
      "price_change_24h": -1.61,
      "tx_volume_u_24h": 12670.821807856,
      "holders": 5359,
      "market_cap": "3919067.72398821617247287098131953",
      "fdv": "3919067.72398821617247287098131953",
      "risk_score": "55"
    },
    {
      "token": "0xae6e307c3fe9e922e5674dbd7f830ed49c014c6b",
      "chain": "eth",
      "symbol": "CREDI",
      "name": "CREDI",
      "logo_url": "https://www.iconaves.com/token_icon/eth/0xae6e307c3fe9e922e5674dbd7f830ed49c014c6b.png",
      "current_price_usd": 0.008011837906259272,
      "price_change_24h": 0.62,
      "tx_volume_u_24h": 9960.291915,
      "holders": 3258,
      "market_cap": "7530954.063427314479131392",
      "fdv": "7530954.063427314479131392",
      "risk_score": "70"
    },
    {
      "token": "0x5f64ab1544d28732f0a24f4713c2c8ec0da089f0",
      "chain": "eth",
      "symbol": "DEXTF",
      "name": "DEXTF",
      "logo_url": "https://www.iconaves.com/token_icon/eth/0x5f64ab1544d28732f0a24f4713c2c8ec0da089f0.png",
      "current_price_usd": 0.1543412362563045,
      "price_change_24h": 1.76,
      "tx_volume_u_24h": 9391.548803847083,
      "holders": 3700,
      "market_cap": "15434123.6256304500000000",
      "fdv": "15434123.6256304500000000",
      "risk_score": "40"
    },
    {
      "token": "0xc221b7e65ffc80de234bbb6667abdd46593d34f0",
      "chain": "eth",
      "symbol": "wCFG",
      "name": "wCFG",
      "logo_url": "https://www.iconaves.com/token_icon/eth/0xc221b7e65ffc80de234bbb6667abdd46593d34f0.png",
      "current_price_usd": 0.16157071443219398,
      "price_change_24h": 5.75,
      "tx_volume_u_24h": 7808.516042,
      "holders": 1,
      "market_cap": "28573261.497630606696358941371894",
      "fdv": "28573261.497630606696358941371894",
      "risk_score": "55"
    },
    {
      "token": "0xc477d038d5420c6a9e0b031712f61c5120090de9",
      "chain": "eth",
      "symbol": "BOSON",
      "name": "Boson Protocol",
      "logo_url": "https://www.iconaves.com/token_icon/eth/0xc477d038d5420c6a9e0b031712f61c5120090de9.png",
      "current_price_usd": 0.13742725194016878,
      "price_change_24h": 6.33,
      "tx_volume_u_24h": 7590.47018705637,
      "holders": 10844,
      "market_cap": "27485450.38803375600000000",
      "fdv": "27485450.38803375600000000",
      "risk_score": "40"
    },
    {
      "token": "0x4e78011ce80ee02d2c3e649fb657e45898257815",
      "chain": "polygon",
      "symbol": "KLIMA",
      "name": "Klima DAO",
      "logo_url": "https://www.iconaves.com/token_icon/polygon/0x4e78011ce80ee02d2c3e649fb657e45898257815.png",
      "current_price_usd": 0.21822518612983546,
      "price_change_24h": -1.65,
      "tx_volume_u_24h": 7374.408126,
      "holders": 34137,
      "market_cap": "4132318.86532674782586249084558834",
      "fdv": "4132318.86532674782586249084558834",
      "risk_score": "66"
    },
    {
      "token": "0xa444ec96ee01bb219a44b285de47bf33c3447ad5",
      "chain": "eth",
      "symbol": "LEOX",
      "name": "LEOX",
      "logo_url": "https://www.iconaves.com/token_icon/eth/0xa444ec96ee01bb219a44b285de47bf33c3447ad5.png",
      "current_price_usd": 0.06997331921172442,
      "price_change_24h": 7.83,
      "tx_volume_u_24h": 6362.656470361483,
      "holders": 11537,
      "market_cap": "4898132.34482070940000000",
      "fdv": "4898132.34482070940000000",
      "risk_score": "55"
    },
    {
      "token": "0x692ac1e363ae34b6b489148152b12e2785a3d8d6",
      "chain": "polygon",
      "symbol": "TRADE",
      "name": "TRADE",
      "logo_url": "https://www.iconaves.com/token_icon/polygon/0x692ac1e363ae34b6b489148152b12e2785a3d8d6.png",
      "current_price_usd": 0.21260030336201916,
      "price_change_24h": 6.43,
      "tx_volume_u_24h": 5628.00926,
      "holders": 9688,
      "market_cap": "15287896.92403220519804280019826085530017704",
      "fdv": "15287896.92403220519804280019826085530017704",
      "risk_score": "70"
    },
    {
      "token": "0xf21661d0d1d76d3ecb8e1b9f1c923dbfffae4097",
      "chain": "eth",
      "symbol": "RIO",
      "name": "Realio Network",
      "logo_url": "https://www.iconaves.com/token_icon/eth/0xf21661d0d1d76d3ecb8e1b9f1c923dbfffae4097.png",
      "current_price_usd": 0.016366763995683244,
      "price_change_24h": -26.21,
      "tx_volume_u_24h": 5335.795643,
      "holders": 33093,
      "market_cap": "1219129.18886742835477648030971248",
      "fdv": "1219129.18886742835477648030971248",
      "risk_score": "55"
    },
    {
      "token": "0x3096e7bfd0878cc65be71f8899bc4cfb57187ba3",
      "chain": "arbitrum",
      "symbol": "RWA",
      "name": "RWA",
      "logo_url": "https://www.iconaves.com/token_icon/arbitrum/0x3096e7bfd0878cc65be71f8899bc4cfb57187ba3.png",
      "current_price_usd": 0.018478707347152214,
      "price_change_24h": 6.41,
      "tx_volume_u_24h": 5311.61084,
      "holders": 2736,
      "market_cap": "3695741.469430442800000000",
      "fdv": "3695741.469430442800000000",
      "risk_score": "55"
    },
    {
      "token": "0x328a268b191ef593b72498a9e8a481c086eb21be",
      "chain": "eth",
      "symbol": "MZERO",
      "name": "MZERO",
      "logo_url": "https://www.iconaves.com/token_icon/eth/0x328a268b191ef593b72498a9e8a481c086eb21be.png",
      "current_price_usd": 0.008876672661360292,
      "price_change_24h": 1.25,
      "tx_volume_u_24h": 3593.596646,
      "holders": 5420,
      "market_cap": "887664.603134230791912400",
      "fdv": "887664.603134230791912400",
      "risk_score": "55"
    },
    {
      "token": "0x5d37abafd5498b0e7af753a2e83bd4f0335aa89f",
      "chain": "bsc",
      "symbol": "WECO",
      "name": "WECOIN",
      "logo_url": "https://www.iconaves.com/token_icon/bsc/0x5d37abafd5498b0e7af753a2e83bd4f0335aa89f.png",
      "current_price_usd": 0.00003225875662531909,
      "price_change_24h": -23.65,
      "tx_volume_u_24h": 2795.512579,
      "holders": 11218,
      "market_cap": "320005.046870598807538639441305454400",
      "fdv": "320005.046870598807538639441305454400",
      "risk_score": "40"
    },
    {
      "token": "0x33e07f5055173cf8febede8b21b12d1e2b523205",
      "chain": "eth",
      "symbol": "ELAND",
      "name": "ELAND",
      "logo_url": "https://www.iconaves.com/token_icon/eth/0x33e07f5055173cf8febede8b21b12d1e2b523205.png",
      "current_price_usd": 0.01122268466069803,
      "price_change_24h": -9.6,
      "tx_volume_u_24h": 2069.5020552222013,
      "holders": 2034,
      "market_cap": "460400.122549609606695890",
      "fdv": "460400.122549609606695890",
      "risk_score": "70"
    },
    {
      "token": "0x708cb02ad77e1b245b1640cee51b3cc844bcaef4",
      "chain": "bsc",
      "symbol": "bELAND",
      "name": "Etherland",
      "logo_url": "https://www.iconaves.com/token_icon/bsc/0x708cb02ad77e1b245b1640cee51b3cc844bcaef4.png",
      "current_price_usd": 0.01117171322191772,
      "price_change_24h": -16.15,
      "tx_volume_u_24h": 1439.2307754457559,
      "holders": 2989,
      "market_cap": "121200.959341840503731766198095200",
      "fdv": "121200.959341840503731766198095200",
      "risk_score": "70"
    },
    {
      "token": "0x33349b282065b0284d756f0577fb39c158f935e6",
      "chain": "eth",
      "symbol": "MPL",
      "name": "Maple",
      "logo_url": "https://www.iconaves.com/token_icon/eth/0x33349b282065b0284d756f0577fb39c158f935e6.png",
      "current_price_usd": 2.3896097010499875,
      "price_change_24h": 47.88,
      "tx_volume_u_24h": 989.181147,
      "holders": 9129,
      "market_cap": "23896097.0104998750000000",
      "fdv": "23896097.0104998750000000",
      "risk_score": "40"
    },
    {
      "token": "0xe0bceef36f3a6efdd5eebfacd591423f8549b9d5",
      "chain": "polygon",
      "symbol": "FACTR",
      "name": "FACTR",
      "logo_url": "https://www.iconaves.com/token_icon/polygon/0xe0bceef36f3a6efdd5eebfacd591423f8549b9d5.png",
      "current_price_usd": 0.024447353337355468,
      "price_change_24h": 6.35,
      "tx_volume_u_24h": 708.1081999871574,
      "holders": 3994,
      "market_cap": "2317255.87110830222047474780592396351528704",
      "fdv": "2317255.87110830222047474780592396351528704",
      "risk_score": "55"
    },
    {
      "token": "0x4a615bb7166210cce20e6642a6f8fb5d4d044496",
      "chain": "eth",
      "symbol": "NAOS",
      "name": "NAOS",
      "logo_url": "https://www.iconaves.com/token_icon/eth/0x4a615bb7166210cce20e6642a6f8fb5d4d044496.png",
      "current_price_usd": 0.0021650917462799394,
      "price_change_24h": 0,
      "tx_volume_u_24h": 335.800351,
      "holders": 2320,
      "market_cap": "131310.475645991330371060490362404",
      "fdv": "474538.589704314184397558392487844",
      "risk_score": "40"
    },
    {
      "token": "0x2ad9addd0d97ec3cdba27f92bf6077893b76ab0b",
      "chain": "eth",
      "symbol": "PLANET",
      "name": "PLANET",
      "logo_url": "https://www.iconaves.com/token_icon/eth/0x2ad9addd0d97ec3cdba27f92bf6077893b76ab0b.png",
      "current_price_usd": 9.402969807697691e-7,
      "price_change_24h": 3.86,
      "tx_volume_u_24h": 141.7558515618935,
      "holders": 24056,
      "market_cap": "940296.9807791720698076976910",
      "fdv": "940296.9807791720698076976910",
      "risk_score": "20"
    },
    {
      "token": "0x08a1c30bbb26425c1031ee9e43fa0b9960742539",
      "chain": "eth",
      "symbol": "LNDX",
      "name": "LNDX",
      "logo_url": "https://www.iconaves.com/token_icon/eth/0x08a1c30bbb26425c1031ee9e43fa0b9960742539.png",
      "current_price_usd": 0.17521904868114255,
      "price_change_24h": 0,
      "tx_volume_u_24h": 30.594493459354094,
      "holders": 2222,
      "market_cap": "11767403.89480489896085021580715",
      "fdv": "11767403.89480489896085021580715",
      "risk_score": "55"
    },
    {
      "token": "0x3269a3c00ab86c753856fd135d97b87facb0d848",
      "chain": "arbitrum",
      "symbol": "FFM",
      "name": "FFM",
      "logo_url": "https://www.iconaves.com/token_icon/arbitrum/0x3269a3c00ab86c753856fd135d97b87facb0d848.png",
      "current_price_usd": 0.0008068588530003828,
      "price_change_24h": 8.28,
      "tx_volume_u_24h": 17.434646417546855,
      "holders": 1920,
      "market_cap": "803766.9488855452474896866776162878940483764",
      "fdv": "803766.9488855452474896866776162878940483764",
      "risk_score": "70"
    },
    {
      "token": "0x120a3879da835a5af037bb2d1456bebd6b54d4ba",
      "chain": "eth",
      "symbol": "RVST",
      "name": "Revest Finance",
      "logo_url": "https://www.iconaves.com/token_icon/eth/0x120a3879da835a5af037bb2d1456bebd6b54d4ba.png",
      "current_price_usd": 0.007115639911377933,
      "price_change_24h": 0,
      "tx_volume_u_24h": 15.759931774846443,
      "holders": 5993,
      "market_cap": "711563.991137793300000000",
      "fdv": "711563.991137793300000000",
      "risk_score": "40"
    },
    {
      "token": "0x2af864fb54b55900cd58d19c7102d9e4fa8d84a3",
      "chain": "base",
      "symbol": "GB",
      "name": "GB",
      "logo_url": "https://www.iconaves.com/token_icon/base/0x2af864fb54b55900cd58d19c7102d9e4fa8d84a3.png",
      "current_price_usd": 0.00047446542955180654,
      "price_change_24h": 4.79,
      "tx_volume_u_24h": 4.43439,
      "holders": 7590,
      "market_cap": "23723.27147759032700000000",
      "fdv": "23723.27147759032700000000",
      "risk_score": "55"
    },
    {
      "token": "0x3d04edc843e74935c09f54cc4b2fe1870e347ac9",
      "chain": "bsc",
      "symbol": "CGT",
      "name": "Curio Governance Token on BSC",
      "logo_url": "https://www.iconaves.com/token_icon/bsc/0x3d04edc843e74935c09f54cc4b2fe1870e347ac9.png",
      "current_price_usd": 0.000008744085626140628,
      "price_change_24h": 0,
      "tx_volume_u_24h": 0.30848453776237866,
      "holders": 2153,
      "market_cap": "1025.097779548265068162585225483911840642252",
      "fdv": "1025.097779548265068162585225483911840642252",
      "risk_score": "100"
    },
    {
      "token": "0x8c49a510756224e887b3d99d00d959f2d86dda1c",
      "chain": "bsc",
      "symbol": "RIO",
      "name": "RIO",
      "logo_url": "https://www.iconaves.com/token_icon/bsc/0x8c49a510756224e887b3d99d00d959f2d86dda1c.png",
      "current_price_usd": 0.0014416457364057756,
      "price_change_24h": 0.02,
      "tx_volume_u_24h": 0.067759,
      "holders": 19501,
      "market_cap": "108123.4302304331700000000",
      "fdv": "108123.4302304331700000000",
      "risk_score": "55"
    },
    {
      "token": "0x912529007bc0d2a5464a6a211ebfe217dfb75dff",
      "chain": "eth",
      "symbol": "CAD",
      "name": "CAD",
      "logo_url": "https://www.iconaves.com/token_icon/eth/0x912529007bc0d2a5464a6a211ebfe217dfb75dff.png",
      "current_price_usd": 0.0006990823596686217,
      "price_change_24h": 0,
      "tx_volume_u_24h": 0,
      "holders": 1418,
      "market_cap": "20181.2796875919266148592316481",
      "fdv": "20181.2796875919266148592316481",
      "risk_score": "55"
    },
    {
      "token": "0x97d0cfeb4fde54b430307c9482d6f79c761fe9b6",
      "chain": "eth",
      "symbol": "EPOCH",
      "name": "Epoch",
      "logo_url": "https://www.iconaves.com/token_icon/eth/0x97d0cfeb4fde54b430307c9482d6f79c761fe9b6.png",
      "current_price_usd": 0.0005132033774650569,
      "price_change_24h": 0,
      "tx_volume_u_24h": 0,
      "holders": 1207,
      "market_cap": "67886.270963230683170004918778180214750889",
      "fdv": "67886.270963230683170004918778180214750889",
      "risk_score": "55"
    },
    {
      "token": "0xe22c452bd2ade15dfc8ad98286bc6bdf0c9219b7",
      "chain": "arbitrum",
      "symbol": "TRADE",
      "name": "TRADE",
      "logo_url": "https://www.iconaves.com/token_icon/arbitrum/0xe22c452bd2ade15dfc8ad98286bc6bdf0c9219b7.png",
      "current_price_usd": 0.1853170709389404,
      "price_change_24h": 0,
      "tx_volume_u_24h": 0,
      "holders": 438,
      "market_cap": "27456.9014230812246973155470012243119188",
      "fdv": "27456.9014230812246973155470012243119188",
      "risk_score": "40"
    }
  ],
  "timestamp": 1746920232543
}