{
  "data": [
    {
      "token": "6p6xgHyF7AeE6TZkSmFsko444wqoP15icUSqi2jfGiPN",
      "chain": "solana",
      "symbol": "TRUMP",
      "name": "OFFICIAL TRUMP",
      "logo_url": "https://www.iconaves.com/token_icon/solana/6p6xgHyF7AeE6TZkSmFsko444wqoP15icUSqi2jfGiPN_1737366143.png",
      "current_price_usd": 10.915590863952334,
      "price_change_24h": -0.98,
      "tx_volume_u_24h": 48400167.443303004,
      "holders": 642034,
      "market_cap": "2183111564.053464043296718332898",
      "fdv": "10915584518.979668879840917108898",
      "risk_score": "55"
    },
    {
      "token": "KMNo3nJsBXfcpJTVhZcXLW7RmTwTt4GVFE7suUBo9sS",
      "chain": "solana",
      "symbol": "KMNO",
      "name": "KMNO",
      "logo_url": "https://www.iconaves.com/token_icon_solana/solana/KMNo3nJsBXfcpJTVhZcXLW7RmTwTt4GVFE7suUBo9sS.png",
      "current_price_usd": 0.06660087834403203,
      "price_change_24h": -17.55,
      "tx_volume_u_24h": 32030206.429108,
      "holders": 52193,
      "market_cap": "666007663.77368251795232339915817",
      "fdv": "666007663.77368251795232339915817",
      "risk_score": "55"
    },
    {
      "token": "MEW1gQWJ3nEXg2qgERiKu7FAFj79PHvQVREQUzScPP5",
      "chain": "solana",
      "symbol": "MEW",
      "name": "MEW",
      "logo_url": "https://www.iconaves.com/token_icon_solana/solana/MEW1gQWJ3nEXg2qgERiKu7FAFj79PHvQVREQUzScPP5.png",
      "current_price_usd": 0.0028378622153673733,
      "price_change_24h": 9.14,
      "tx_volume_u_24h": 31313306.260188,
      "holders": 174142,
      "market_cap": "252246500.910239192450589140664208",
      "fdv": "252246500.910239192450589140664208",
      "risk_score": "55"
    },
    {
      "token": "8xhH7tDB6m1akaexEYsn8Qkb58r6EY8MA4t958mipump",
      "chain": "solana",
      "symbol": "mog/acc",
      "name": "mog/acc",
      "logo_url": "https://www.iconaves.com/ipfs/pump/8xhH7tDB6m1akaexEYsn8Qkb58r6EY8MA4t958mipump_147.webp",
      "current_price_usd": 0.0007599500216863435,
      "price_change_24h": 1145.43,
      "tx_volume_u_24h": 23438148.889475,
      "holders": 5086,
      "market_cap": "759950.0216863435000000000",
      "fdv": "759950.0216863435000000000",
      "risk_score": "0"
    },
    {
      "token": "EJ281Pgg8YuWQoJiqcWVkW1LcuXG1MexMSo6WnVYwhFw",
      "chain": "solana",
      "symbol": "DETX",
      "name": "DETX",
      "logo_url": "",
      "current_price_usd": 0.002307096681103272,
      "price_change_24h": 388.2,
      "tx_volume_u_24h": 19646285.072845,
      "holders": 5498,
      "market_cap": "2307096.681103272000000000",
      "fdv": "2307096.681103272000000000",
      "risk_score": "55"
    },
    {
      "token": "83mCRQJzvKMeQd9wJbZDUCTPgRbZMDoPdMSx5Sf1pump",
      "chain": "solana",
      "symbol": "LLJEFFY",
      "name": "LLJEFFY",
      "logo_url": "https://www.iconaves.com/ipfs/pump/83mCRQJzvKMeQd9wJbZDUCTPgRbZMDoPdMSx5Sf1pump_147.webp",
      "current_price_usd": 0.026132936024922324,
      "price_change_24h": -32.44,
      "tx_volume_u_24h": 17672910.068038,
      "holders": 5974,
      "market_cap": "3263801.239812354899185588600332",
      "fdv": "3263801.239812354899185588600332",
      "risk_score": "0"
    },
    {
      "token": "7tdvVHWcLqMgMRZ5rFo5fnQVvKnbHfjFx54BoVee8gTS",
      "chain": "solana",
      "symbol": "TRUMP",
      "name": "TRUMP",
      "logo_url": "",
      "current_price_usd": 0.0010054674898540093,
      "price_change_24h": -47.12,
      "tx_volume_u_24h": 17079720.894375,
      "holders": 23690,
      "market_cap": "1005467.4592056428707771258881156",
      "fdv": "1005467.4592056428707771258881156",
      "risk_score": "55"
    },
    {
      "token": "E6bhiXpo7XbdVSNa2XJH3BQ7aUHQdut75w1GQdQTUnYr",
      "chain": "solana",
      "symbol": "69420",
      "name": "69420",
      "logo_url": "",
      "current_price_usd": 0.0013169495682227718,
      "price_change_24h": 294.58,
      "tx_volume_u_24h": 16643742.467025,
      "holders": 2370,
      "market_cap": "1316949.5682227718000000000",
      "fdv": "1316949.5682227718000000000",
      "risk_score": "55"
    },
    {
      "token": "9j6twpYWrV1ueJok76D9YK8wJTVoG9Zy8spC7wnTpump",
      "chain": "solana",
      "symbol": "urmom ",
      "name": "urmom ",
      "logo_url": "https://www.iconaves.com/ipfs/pump/9j6twpYWrV1ueJok76D9YK8wJTVoG9Zy8spC7wnTpump_147_20250505011853.webp",
      "current_price_usd": 0.010445284477049958,
      "price_change_24h": -14.46,
      "tx_volume_u_24h": 15034477.57805,
      "holders": 6147,
      "market_cap": "10445284.477049958000000000",
      "fdv": "10445284.477049958000000000",
      "risk_score": "0"
    },
    {
      "token": "Hg8bKz4mvs8KNj9zew1cEF9tDw1x2GViB4RFZjVEmfrD",
      "chain": "solana",
      "symbol": "TDCCP",
      "name": "TDCCP",
      "logo_url": "https://www.iconaves.com/token_icon_solana/solana/Hg8bKz4mvs8KNj9zew1cEF9tDw1x2GViB4RFZjVEmfrD.png",
      "current_price_usd": 1.128697214268435,
      "price_change_24h": -11.42,
      "tx_volume_u_24h": 14799743.647637,
      "holders": 11381,
      "market_cap": "722366195.631118526701837980861435",
      "fdv": "722366195.631118526701837980861435",
      "risk_score": "55"
    },
    {
      "token": "EBPdRQ7TAjRi1KYjG9bVQiQ8BYDXbKZtrwPKQMRA7d5j",
      "chain": "solana",
      "symbol": "UTRUMP",
      "name": "UTRUMP",
      "logo_url": "",
      "current_price_usd": 0.005032968838865611,
      "price_change_24h": -23.69,
      "tx_volume_u_24h": 14131578.983517,
      "holders": 14033,
      "market_cap": "5032968.838865611000000000",
      "fdv": "5032968.838865611000000000",
      "risk_score": "55"
    },
    {
      "token": "38PgzpJYu2HkiYvV8qePFakB8tuobPdGm2FFEn7Dpump",
      "chain": "solana",
      "symbol": "gork",
      "name": "gork",
      "logo_url": "https://www.iconaves.com/ipfs/pump/38PgzpJYu2HkiYvV8qePFakB8tuobPdGm2FFEn7Dpump_147.webp",
      "current_price_usd": 0.027187235129974157,
      "price_change_24h": -16.46,
      "tx_volume_u_24h": 14112697.714867,
      "holders": 22248,
      "market_cap": "27186861.361904578375567365826686",
      "fdv": "27186861.361904578375567365826686",
      "risk_score": "0"
    },
    {
      "token": "DqMPaULkovCjp8qP2sb6BnZY77reBRKWRNk6sFJHXRDh",
      "chain": "solana",
      "symbol": "STDM",
      "name": "STDM",
      "logo_url": "",
      "current_price_usd": 0.002425472193932973,
      "price_change_24h": 3.27,
      "tx_volume_u_24h": 13763625.615162,
      "holders": 4521,
      "market_cap": "2425472.193932973000000000",
      "fdv": "2425472.193932973000000000",
      "risk_score": "55"
    },
    {
      "token": "HeLp6NuQkmYB4pYWo2zYs22mESHXPQYzXbB8n4V98jwC",
      "chain": "solana",
      "symbol": "ai16z",
      "name": "ai16z",
      "logo_url": "https://www.iconaves.com/token_icon/solana/HeLp6NuQkmYB4pYWo2zYs22mESHXPQYzXbB8n4V98jwC.png",
      "current_price_usd": 0.26530638907109044,
      "price_change_24h": 1.17,
      "tx_volume_u_24h": 13267596.322241,
      "holders": 114395,
      "market_cap": "291836666.72979293892798467214864224",
      "fdv": "291836666.72979293892798467214864224",
      "risk_score": "55"
    },
    {
      "token": "9ZJZ9iMsKLv4boFwQ37CwGHthJXXszZt521pXYgoJWxR",
      "chain": "solana",
      "symbol": "OT",
      "name": "OT",
      "logo_url": "",
      "current_price_usd": 0.01016481148209462,
      "price_change_24h": 2028.63,
      "tx_volume_u_24h": 13141845.909619,
      "holders": 5017,
      "market_cap": "10164811.48209462000000000",
      "fdv": "10164811.48209462000000000",
      "risk_score": "55"
    },
    {
      "token": "J5HrxbWTNj2GdFSwVbihPXTL2YPN5yWYLEQH1nVTE9u3",
      "chain": "solana",
      "symbol": "olo",
      "name": "olo",
      "logo_url": "",
      "current_price_usd": 0.001117183301630305,
      "price_change_24h": 188.4,
      "tx_volume_u_24h": 12004782.337606,
      "holders": 3442,
      "market_cap": "1117183.301630305000000000",
      "fdv": "1117183.301630305000000000",
      "risk_score": "55"
    },
    {
      "token": "DitHyRMQiSDhn5cnKMJV2CDDt6sVct96YrECiM49pump",
      "chain": "solana",
      "symbol": "House",
      "name": "House",
      "logo_url": "https://www.iconaves.com/ipfs/pump/DitHyRMQiSDhn5cnKMJV2CDDt6sVct96YrECiM49pump.png",
      "current_price_usd": 0.04355442416464281,
      "price_change_24h": -17.4,
      "tx_volume_u_24h": 11365752.028754,
      "holders": 21931,
      "market_cap": "43500415.93167959865980603211546",
      "fdv": "43500415.93167959865980603211546",
      "risk_score": "40"
    },
    {
      "token": "BvVLqD88KoPUA9dhi8BLMUeeeDyDpknFYwkzFr35u3Vo",
      "chain": "solana",
      "symbol": "VETA",
      "name": "VETA",
      "logo_url": "",
      "current_price_usd": 0.0029995333261312227,
      "price_change_24h": -2.84,
      "tx_volume_u_24h": 11219146.371943,
      "holders": 5960,
      "market_cap": "2999533.3261312227000000000",
      "fdv": "2999533.3261312227000000000",
      "risk_score": "55"
    },
    {
      "token": "9BB6NFEcjBCtnNLFko2FqVQBq8HHM13kCyYcdQbgpump",
      "chain": "solana",
      "symbol": "Fartcoin",
      "name": "Fartcoin",
      "logo_url": "https://www.iconaves.com/token_icon_solana/solana/9BB6NFEcjBCtnNLFko2FqVQBq8HHM13kCyYcdQbgpump.png",
      "current_price_usd": 1.0241959329997374,
      "price_change_24h": -5.53,
      "tx_volume_u_24h": 10698839.569217,
      "holders": 148472,
      "market_cap": "1024187956.2985928432641962882",
      "fdv": "1024187956.2985928432641962882",
      "risk_score": "40"
    },
    {
      "token": "8hhRHZkoCwLojdSthxu3Ho5K2j4BZHnSZ93HZjd4Mxo6",
      "chain": "solana",
      "symbol": "LFG",
      "name": "LFG",
      "logo_url": "",
      "current_price_usd": 0.0012232137195796755,
      "price_change_24h": 2.35,
      "tx_volume_u_24h": 9990129.526875,
      "holders": 14157,
      "market_cap": "1223213.7058197884041421351688180",
      "fdv": "1223213.7058197884041421351688180",
      "risk_score": "55"
    },
    {
      "token": "FZRh6uAar3gEJb53ruHNjHibCPqiGHghfGiSRVeFpump",
      "chain": "solana",
      "symbol": "CB",
      "name": "CB",
      "logo_url": "https://www.iconaves.com/ipfs/pump/FZRh6uAar3gEJb53ruHNjHibCPqiGHghfGiSRVeFpump_147.webp",
      "current_price_usd": 0.0009244169473970046,
      "price_change_24h": -52.54,
      "tx_volume_u_24h": 8900628.783157,
      "holders": 4361,
      "market_cap": "924416.9473970046000000000",
      "fdv": "924416.9473970046000000000",
      "risk_score": "0"
    },
    {
      "token": "G1jydhghPMLBXRFPR3wyJ9HbpKPR3Rv7M8Yakfo5pump",
      "chain": "solana",
      "symbol": "stickman",
      "name": "stickman",
      "logo_url": "https://www.iconaves.com/ipfs/pump/G1jydhghPMLBXRFPR3wyJ9HbpKPR3Rv7M8Yakfo5pump_147.webp",
      "current_price_usd": 0.0013458998871747833,
      "price_change_24h": -54.16,
      "tx_volume_u_24h": 8537958.799275,
      "holders": 5247,
      "market_cap": "1345899.8871747833000000000",
      "fdv": "1345899.8871747833000000000",
      "risk_score": "0"
    },
    {
      "token": "CemfzAqaUGDof18CEdB1jv2CeECGQqMjWEMh8772pump",
      "chain": "solana",
      "symbol": "BABIFY",
      "name": "BABIFY",
      "logo_url": "https://www.iconaves.com/ipfs/pump/CemfzAqaUGDof18CEdB1jv2CeECGQqMjWEMh8772pump_147.webp",
      "current_price_usd": 0.0009859344187123761,
      "price_change_24h": 1512.35,
      "tx_volume_u_24h": 8230521.666603,
      "holders": 2805,
      "market_cap": "985934.4187123761000000000",
      "fdv": "985934.4187123761000000000",
      "risk_score": "0"
    },
    {
      "token": "9B82KVX3TyYAJ3UKSPJVwMLqmkazYhRUNy42XAA1A1a3",
      "chain": "solana",
      "symbol": "$BPEARL",
      "name": "$BPEARL",
      "logo_url": "",
      "current_price_usd": 0.0003486269852780768,
      "price_change_24h": -2.19,
      "tx_volume_u_24h": 7816661.578445,
      "holders": 2036,
      "market_cap": "348626.9852780768000000000",
      "fdv": "348626.9852780768000000000",
      "risk_score": "55"
    },
    {
      "token": "4fZdRopQjUDnkjzXhJqWx79RFuHBbNoK2y1R9ZKxWEYZ",
      "chain": "solana",
      "symbol": "Liang",
      "name": "Liang",
      "logo_url": "",
      "current_price_usd": 0.002615382163218306,
      "price_change_24h": 85.05,
      "tx_volume_u_24h": 7270274.604053,
      "holders": 13453,
      "market_cap": "2615382.163218306000000000",
      "fdv": "2615382.163218306000000000",
      "risk_score": "55"
    },
    {
      "token": "8x5VqbHA8D7NkD52uNuS5nnt3PwA8pLD34ymskeSo2Wn",
      "chain": "solana",
      "symbol": "ZEREBRO",
      "name": "ZEREBRO",
      "logo_url": "https://www.iconaves.com/token_icon_solana/solana/8x5VqbHA8D7NkD52uNuS5nnt3PwA8pLD34ymskeSo2Wn.png",
      "current_price_usd": 0.03627683828761782,
      "price_change_24h": -10.78,
      "tx_volume_u_24h": 7069704.51792,
      "holders": 76963,
      "market_cap": "36275288.08664592952303486791744",
      "fdv": "36275288.08664592952303486791744",
      "risk_score": "40"
    },
    {
      "token": "5W843JJmuRu1qjdUMpXDqtDvTDWBYhkGfoxFXTABpump",
      "chain": "solana",
      "symbol": "DOG",
      "name": "DOG",
      "logo_url": "",
      "current_price_usd": 0.00016016547444982088,
      "price_change_24h": 164.25,
      "tx_volume_u_24h": 6956048.968774,
      "holders": 2267,
      "market_cap": "160165.47444982088000000000",
      "fdv": "160165.47444982088000000000",
      "risk_score": "40"
    },
    {
      "token": "CL2bvqdTtYQqhwQC1Ad5GZ7cedW9RrbtUK4AZs9Bpump",
      "chain": "solana",
      "symbol": "pitcoin",
      "name": "pitcoin",
      "logo_url": "https://www.iconaves.com/ipfs/pump/CL2bvqdTtYQqhwQC1Ad5GZ7cedW9RrbtUK4AZs9Bpump_147.webp",
      "current_price_usd": 0.000060643398608474484,
      "price_change_24h": 1,
      "tx_volume_u_24h": 6597882.110901,
      "holders": 1493,
      "market_cap": "60643.398608474484000000000",
      "fdv": "60643.398608474484000000000",
      "risk_score": "0"
    },
    {
      "token": "3AJojR2uCYkijobWHkCeGLaX65o5MQbMn3hGfGYtp66a",
      "chain": "solana",
      "symbol": "OPENAG",
      "name": "OPENAG",
      "logo_url": "",
      "current_price_usd": 0.0027624683036804147,
      "price_change_24h": -45.06,
      "tx_volume_u_24h": 6419470.742363,
      "holders": 5794,
      "market_cap": "2762468.3036804147000000000",
      "fdv": "2762468.3036804147000000000",
      "risk_score": "55"
    },
    {
      "token": "9BqPvc9vPBdcVtez6UYiFEeqTSYqxypF4f1CmtaZpump",
      "chain": "solana",
      "symbol": "vampcoin2",
      "name": "vampcoin2",
      "logo_url": "https://www.iconaves.com/ipfs/pump/9BqPvc9vPBdcVtez6UYiFEeqTSYqxypF4f1CmtaZpump_147.webp",
      "current_price_usd": 0.0047018340549289765,
      "price_change_24h": 60.85,
      "tx_volume_u_24h": 6162633.54025,
      "holders": 1790,
      "market_cap": "4701834.0549289765000000000",
      "fdv": "4701834.0549289765000000000",
      "risk_score": "0"
    },
    {
      "token": "2zMMhcVQEXDtdE6vsFS7S7D5oUodfJHE8vd1gnBouauv",
      "chain": "solana",
      "symbol": "PENGU",
      "name": "PENGU",
      "logo_url": "https://www.iconaves.com/token_icon_solana/solana/2zMMhcVQEXDtdE6vsFS7S7D5oUodfJHE8vd1gnBouauv.png",
      "current_price_usd": 0.011272043522070502,
      "price_change_24h": -0.04,
      "tx_volume_u_24h": 6149658.426085,
      "holders": 516157,
      "market_cap": "864833205.151282616940839014053836",
      "fdv": "864833205.151282616940839014053836",
      "risk_score": "55"
    },
    {
      "token": "9cTc8GMh3KoBcn2VHHLeN9AZzfvjwf1PQYpgRstJ2eNf",
      "chain": "solana",
      "symbol": "3D",
      "name": "3D",
      "logo_url": "",
      "current_price_usd": 0.0024354252498370063,
      "price_change_24h": 44.54,
      "tx_volume_u_24h": 5861056.298274,
      "holders": 3415,
      "market_cap": "2435425.2498370063000000000",
      "fdv": "2435425.2498370063000000000",
      "risk_score": "55"
    },
    {
      "token": "FtUEW73K6vEYHfbkfpdBZfWpxgQar2HipGdbutEhpump",
      "chain": "solana",
      "symbol": "titcoin",
      "name": "titcoin",
      "logo_url": "https://www.iconaves.com/ipfs/pump/FtUEW73K6vEYHfbkfpdBZfWpxgQar2HipGdbutEhpump.png",
      "current_price_usd": 0.033218843411187526,
      "price_change_24h": 6.54,
      "tx_volume_u_24h": 5517172.636865,
      "holders": 19417,
      "market_cap": "33202307.041591279422089326968606",
      "fdv": "33202307.041591279422089326968606",
      "risk_score": "40"
    },
    {
      "token": "7GCihgDB8fe6KNjn2MYtkzZcRjQy3t9GHdC8uHYmW2hr",
      "chain": "solana",
      "symbol": "POPCAT",
      "name": "POPCAT",
      "logo_url": "https://www.iconaves.com/token_icon_solana/solana/7GCihgDB8fe6KNjn2MYtkzZcRjQy3t9GHdC8uHYmW2hr.png",
      "current_price_usd": 0.45237465213529604,
      "price_change_24h": 12.99,
      "tx_volume_u_24h": 5424065.297334,
      "holders": 137632,
      "market_cap": "443300019.6197431123257085385160024",
      "fdv": "443300019.6197431123257085385160024",
      "risk_score": "40"
    },
    {
      "token": "Grass7B4RdKfBCjTKgSqnXkqjwiGvQyFbuSCUJr3XXjs",
      "chain": "solana",
      "symbol": "GRASS",
      "name": "GRASS",
      "logo_url": "https://www.iconaves.com/token_icon/solana/Grass7B4RdKfBCjTKgSqnXkqjwiGvQyFbuSCUJr3XXjs.png",
      "current_price_usd": 1.5205009401458964,
      "price_change_24h": 1.04,
      "tx_volume_u_24h": 5014329.211629,
      "holders": 333624,
      "market_cap": "1520493750.7178128532746871379633648",
      "fdv": "1520493750.7178128532746871379633648",
      "risk_score": "40"
    },
    {
      "token": "A7S4UkbpAXSVfG196Qvr8TMvpvx3Lz2Q4X2RecuApump",
      "chain": "solana",
      "symbol": "MrLeast",
      "name": "MrLeast",
      "logo_url": "https://www.iconaves.com/ipfs/pump/A7S4UkbpAXSVfG196Qvr8TMvpvx3Lz2Q4X2RecuApump_147.webp",
      "current_price_usd": 0.002024747791987128,
      "price_change_24h": 387.45,
      "tx_volume_u_24h": 4948402.76021,
      "holders": 1708,
      "market_cap": "2024714.385958797443045313048",
      "fdv": "2024714.385958797443045313048",
      "risk_score": "0"
    },
    {
      "token": "Bsow2wFkVzy1itJnhLke6VRTqoEkYQZp7kbwPtS87FyN",
      "chain": "solana",
      "symbol": "GIGGLES",
      "name": "GIGGLES",
      "logo_url": "",
      "current_price_usd": 0.0006355253978598671,
      "price_change_24h": 720.96,
      "tx_volume_u_24h": 4754811.138374,
      "holders": 1373,
      "market_cap": "635525.3978598671000000000",
      "fdv": "635525.3978598671000000000",
      "risk_score": "55"
    },
    {
      "token": "5UUH9RTDiSpq6HKS6bp4NdU9PNJpXRXuiw6ShBTBhgH2",
      "chain": "solana",
      "symbol": "TROLL",
      "name": "TROLL",
      "logo_url": "https://www.iconaves.com/token_icon/solana/5UUH9RTDiSpq6HKS6bp4NdU9PNJpXRXuiw6ShBTBhgH2.png",
      "current_price_usd": 0.020581400343414512,
      "price_change_24h": -9.29,
      "tx_volume_u_24h": 4726348.998799,
      "holders": 14415,
      "market_cap": "20560778.232875862122602472904928",
      "fdv": "20560778.232875862122602472904928",
      "risk_score": "40"
    },
    {
      "token": "76EDL5qNcte2ZH29quTaFzagXjWAEY83CATEjyA6pump",
      "chain": "solana",
      "symbol": "gork",
      "name": "gork",
      "logo_url": "https://www.iconaves.com/ipfs/pump/76EDL5qNcte2ZH29quTaFzagXjWAEY83CATEjyA6pump.png",
      "current_price_usd": 0.004066012929226578,
      "price_change_24h": 6.07,
      "tx_volume_u_24h": 4626586.351429,
      "holders": 2404,
      "market_cap": "4065764.655699902482071831975504",
      "fdv": "4065764.655699902482071831975504",
      "risk_score": "0"
    },
    {
      "token": "Ce2gx9KGXJ6C9Mp5b5x1sn9Mg87JwEbrQby4Zqo3pump",
      "chain": "solana",
      "symbol": "neet",
      "name": "neet",
      "logo_url": "https://www.iconaves.com/ipfs/pump/Ce2gx9KGXJ6C9Mp5b5x1sn9Mg87JwEbrQby4Zqo3pump.png",
      "current_price_usd": 0.011227922684994174,
      "price_change_24h": 6.78,
      "tx_volume_u_24h": 4526087.01579,
      "holders": 6191,
      "market_cap": "11227585.205916564680095251275376",
      "fdv": "11227585.205916564680095251275376",
      "risk_score": "0"
    },
    {
      "token": "BPiz36uNt76RjmfH2ZLFD7xAnB4QJ1roh1q86NHupump",
      "chain": "solana",
      "symbol": "urgay",
      "name": "urgay",
      "logo_url": "https://www.iconaves.com/ipfs/pump/BPiz36uNt76RjmfH2ZLFD7xAnB4QJ1roh1q86NHupump_147.webp",
      "current_price_usd": 0.0014295588078576385,
      "price_change_24h": 2220.23,
      "tx_volume_u_24h": 4501320.034046,
      "holders": 2199,
      "market_cap": "1429558.8078576385000000000",
      "fdv": "1429558.8078576385000000000",
      "risk_score": "0"
    },
    {
      "token": "DKu9kykSfbN5LBfFXtNNDPaX35o4Fv6vJ9FKk7pZpump",
      "chain": "solana",
      "symbol": "AVA",
      "name": "AVA",
      "logo_url": "https://www.iconaves.com/token_icon_solana/solana/DKu9kykSfbN5LBfFXtNNDPaX35o4Fv6vJ9FKk7pZpump.png",
      "current_price_usd": 0.0815250730031908,
      "price_change_24h": 8.76,
      "tx_volume_u_24h": 3701905.915889056,
      "holders": 54395,
      "market_cap": "81514351.5930071888699488714884",
      "fdv": "81514351.5930071888699488714884",
      "risk_score": "40"
    },
    {
      "token": "9PR7nCP9DpcUotnDPVLUBUZKu5WAYkwrCUx9wDnSpump",
      "chain": "solana",
      "symbol": "Ban",
      "name": "Comedian",
      "logo_url": "https://www.iconaves.com/token_icon/solana/9PR7nCP9DpcUotnDPVLUBUZKu5WAYkwrCUx9wDnSpump_1737366390.png",
      "current_price_usd": 0.06187771993952045,
      "price_change_24h": 25.35,
      "tx_volume_u_24h": 3588645.060653,
      "holders": 28413,
      "market_cap": "59557258.89966136357359547260195",
      "fdv": "59557258.89966136357359547260195",
      "risk_score": "40"
    },
    {
      "token": "2o86pbkvCVru88TLtsBthcHHn4aR2yEUapPKbYtmpump",
      "chain": "solana",
      "symbol": "Chewy",
      "name": "Chewy",
      "logo_url": "https://www.iconaves.com/ipfs/pump/2o86pbkvCVru88TLtsBthcHHn4aR2yEUapPKbYtmpump_147.webp",
      "current_price_usd": 0.0005134845504467321,
      "price_change_24h": 33.23,
      "tx_volume_u_24h": 3378019.529739,
      "holders": 1645,
      "market_cap": "513484.5504467321000000000",
      "fdv": "513484.5504467321000000000",
      "risk_score": "0"
    },
    {
      "token": "6iCySyZzEeJyjb6sVRLc5F9HLbm1tQUhr6dohvYDpump",
      "chain": "solana",
      "symbol": "HOTEL",
      "name": "HOTEL",
      "logo_url": "https://www.iconaves.com/ipfs/pump/6iCySyZzEeJyjb6sVRLc5F9HLbm1tQUhr6dohvYDpump_147.webp",
      "current_price_usd": 0.00022317142506932274,
      "price_change_24h": 268.13,
      "tx_volume_u_24h": 3254333.911407,
      "holders": 2245,
      "market_cap": "223171.42506932274000000000",
      "fdv": "223171.42506932274000000000",
      "risk_score": "0"
    },
    {
      "token": "8h3jsXbvBRPKGGRPhoYRHr7ca8qH3tBeaE2S93X1pump",
      "chain": "solana",
      "symbol": "DRA",
      "name": "DRA",
      "logo_url": "https://www.iconaves.com/ipfs/pump/8h3jsXbvBRPKGGRPhoYRHr7ca8qH3tBeaE2S93X1pump_147.webp",
      "current_price_usd": 0.002649469153247112,
      "price_change_24h": -24.39,
      "tx_volume_u_24h": 3158526.062665,
      "holders": 3218,
      "market_cap": "2648848.54500162137720204912592",
      "fdv": "2648848.54500162137720204912592",
      "risk_score": "0"
    },
    {
      "token": "boopkpWqe68MSxLqBGogs8ZbUDN4GXaLhFwNP7mpP1i",
      "chain": "solana",
      "symbol": "BOOP",
      "name": "BOOP",
      "logo_url": "https://www.iconaves.com/token_icon_solana/solana/boopkpWqe68MSxLqBGogs8ZbUDN4GXaLhFwNP7mpP1i.png",
      "current_price_usd": 0.23587906161745828,
      "price_change_24h": 5.19,
      "tx_volume_u_24h": 3124182.316537,
      "holders": 8791,
      "market_cap": "235879024.37627002648396603216186616",
      "fdv": "235879024.37627002648396603216186616",
      "risk_score": "55"
    },
    {
      "token": "8ncucXv6U6epZKHPbgaEBcEK399TpHGKCquSt4RnmX4f",
      "chain": "solana",
      "symbol": "TRENCHER",
      "name": "TRENCHER",
      "logo_url": "https://www.iconaves.com/ipfs/pump/8ncucXv6U6epZKHPbgaEBcEK399TpHGKCquSt4RnmX4f_20250424152152.png",
      "current_price_usd": 0.003621045729897708,
      "price_change_24h": -33.09,
      "tx_volume_u_24h": 3050189.686887,
      "holders": 7981,
      "market_cap": "3620619.564910427003579545164876",
      "fdv": "3620619.564910427003579545164876",
      "risk_score": "40"
    },
    {
      "token": "8sv4W4uQ9qML87Kr2XFkYBDwsiFEJVZZ1ScsM71Hpump",
      "chain": "solana",
      "symbol": "BWAH",
      "name": "BWAH",
      "logo_url": "https://www.iconaves.com/ipfs/pump/8sv4W4uQ9qML87Kr2XFkYBDwsiFEJVZZ1ScsM71Hpump_147.webp",
      "current_price_usd": 0.00026356089749676373,
      "price_change_24h": -65.05,
      "tx_volume_u_24h": 2678331.078696,
      "holders": 3668,
      "market_cap": "263560.89749676373000000000",
      "fdv": "263560.89749676373000000000",
      "risk_score": "0"
    },
    {
      "token": "GkyPYa7NnCFbduLknCfBfP7p8564X1VZhwZYJ6CZpump",
      "chain": "solana",
      "symbol": "CHILLHOUSE",
      "name": "CHILLHOUSE",
      "logo_url": "https://www.iconaves.com/ipfs/pump/GkyPYa7NnCFbduLknCfBfP7p8564X1VZhwZYJ6CZpump.png",
      "current_price_usd": 0.0017947478286130618,
      "price_change_24h": -43.41,
      "tx_volume_u_24h": 2633020.946368,
      "holders": 4150,
      "market_cap": "1794641.6579883592009464466782788",
      "fdv": "1794641.6579883592009464466782788",
      "risk_score": "0"
    },
    {
      "token": "9wK8yN6iz1ie5kEJkvZCTxyN1x5sTdNfx8yeMY8Ebonk",
      "chain": "solana",
      "symbol": "Hosico",
      "name": "Hosico",
      "logo_url": "https://www.iconaves.com/ipfs/bonk/9wK8yN6iz1ie5kEJkvZCTxyN1x5sTdNfx8yeMY8Ebonk.png",
      "current_price_usd": 0.02358063266620251,
      "price_change_24h": -8.04,
      "tx_volume_u_24h": 2618285.493168,
      "holders": 5785,
      "market_cap": "23580593.28569061715310713635477",
      "fdv": "23580593.28569061715310713635477",
      "risk_score": "40"
    },
    {
      "token": "2Wu1g2ft7qZHfTpfzP3wLdfPeV1is4EwQ3CXBfRYAciD",
      "chain": "solana",
      "symbol": "GOHOME",
      "name": "GOHOME",
      "logo_url": "https://www.iconaves.com/token_icon_solana/solana/2Wu1g2ft7qZHfTpfzP3wLdfPeV1is4EwQ3CXBfRYAciD.png",
      "current_price_usd": 252.32083705880538,
      "price_change_24h": -1.56,
      "tx_volume_u_24h": 2606538.082884568,
      "holders": 22209,
      "market_cap": "2523112351.00675060471609033656",
      "fdv": "2523112351.00675060471609033656",
      "risk_score": "55"
    },
    {
      "token": "8BtoThi2ZoXnF7QQK1Wjmh2JuBw9FjVvhnGMVZ2vpump",
      "chain": "solana",
      "symbol": "DARK",
      "name": "DARK",
      "logo_url": "https://www.iconaves.com/token_icon_solana/solana/8BtoThi2ZoXnF7QQK1Wjmh2JuBw9FjVvhnGMVZ2vpump.png",
      "current_price_usd": 0.010995133216857847,
      "price_change_24h": -22.26,
      "tx_volume_u_24h": 2595625.553842,
      "holders": 13236,
      "market_cap": "10993011.528343511842581183385328",
      "fdv": "10993011.528343511842581183385328",
      "risk_score": "40"
    },
    {
      "token": "JDzPbXboQYWVmdxXS3LbvjM52RtsV1QaSv2AzoCiai2o",
      "chain": "solana",
      "symbol": "FO",
      "name": "FO",
      "logo_url": "https://www.iconaves.com/token_icon_solana/solana/JDzPbXboQYWVmdxXS3LbvjM52RtsV1QaSv2AzoCiai2o.png",
      "current_price_usd": 0.7115473913043479,
      "price_change_24h": -0.99,
      "tx_volume_u_24h": 2593234.09169,
      "holders": 149202,
      "market_cap": "710359060.019752066637429885755",
      "fdv": "710359060.019752066637429885755",
      "risk_score": "55"
    },
    {
      "token": "8oosbx7jJrZxm5m4ThKhBpvwwG4QpoAe6i4GiG19pump",
      "chain": "solana",
      "symbol": "Wizard",
      "name": "Wizard",
      "logo_url": "https://www.iconaves.com/ipfs/pump/8oosbx7jJrZxm5m4ThKhBpvwwG4QpoAe6i4GiG19pump.png",
      "current_price_usd": 0.001635028104800955,
      "price_change_24h": -34.48,
      "tx_volume_u_24h": 2537431.849146,
      "holders": 6681,
      "market_cap": "1634782.571716585876886937818985",
      "fdv": "1634782.571716585876886937818985",
      "risk_score": "40"
    },
    {
      "token": "FeR8VBqNRSUD5NtXAj2n3j1dAHkZHfyDktKuLXD4pump",
      "chain": "solana",
      "symbol": "jellyjelly",
      "name": "jelly-my-jelly",
      "logo_url": "https://www.iconaves.com/token_icon_solana/solana/FeR8VBqNRSUD5NtXAj2n3j1dAHkZHfyDktKuLXD4pump.png",
      "current_price_usd": 0.033773570343146035,
      "price_change_24h": -1.75,
      "tx_volume_u_24h": 2209933.009776,
      "holders": 32703,
      "market_cap": "33772655.470302162094187684129745",
      "fdv": "33772655.470302162094187684129745",
      "risk_score": "40"
    },
    {
      "token": "C3DwDjT17gDvvCYC2nsdGHxDHVmQRdhKfpAdqQ29pump",
      "chain": "solana",
      "symbol": "RFC",
      "name": "RFC",
      "logo_url": "https://www.iconaves.com/ipfs/pump/C3DwDjT17gDvvCYC2nsdGHxDHVmQRdhKfpAdqQ29pump.png",
      "current_price_usd": 0.011934363089627422,
      "price_change_24h": 6.12,
      "tx_volume_u_24h": 2121004.898655,
      "holders": 13281,
      "market_cap": "11932726.538549672790863194859010",
      "fdv": "11932726.538549672790863194859010",
      "risk_score": "40"
    },
    {
      "token": "Df6yfrKC8kZE3KNkrHERKzAetSxbrWeniQfyJY4Jpump",
      "chain": "solana",
      "symbol": "CHILLGUY",
      "name": "CHILLGUY",
      "logo_url": "https://www.iconaves.com/token_icon_solana/solana/Df6yfrKC8kZE3KNkrHERKzAetSxbrWeniQfyJY4Jpump.png",
      "current_price_usd": 0.04971695336117784,
      "price_change_24h": -5.63,
      "tx_volume_u_24h": 2070252.64213,
      "holders": 132240,
      "market_cap": "49714663.51900755087816976932816",
      "fdv": "49714663.51900755087816976932816",
      "risk_score": "40"
    },
    {
      "token": "JmMRbLcKgNCu17yHZDAn4strE5NjmWJ4pCeJ7s7boop",
      "chain": "solana",
      "symbol": "Boopa",
      "name": "Boopa",
      "logo_url": "https://www.iconaves.com/token_icon/solana/JmMRbLcKgNCu17yHZDAn4strE5NjmWJ4pCeJ7s7boop.png",
      "current_price_usd": 0.0038471194628797,
      "price_change_24h": -0.29,
      "tx_volume_u_24h": 2041459.268929,
      "holders": 10317,
      "market_cap": "3823092.604331078757872602711946",
      "fdv": "3823092.604331078757872602711946",
      "risk_score": "40"
    },
    {
      "token": "5VsVZBRZ34bf6LbpsJ5kwZZUFii5Gj2xKVc5BgRGpump",
      "chain": "solana",
      "symbol": "MFERS",
      "name": "MFERS",
      "logo_url": "https://www.iconaves.com/ipfs/pump/5VsVZBRZ34bf6LbpsJ5kwZZUFii5Gj2xKVc5BgRGpump_147.webp",
      "current_price_usd": 0.0002937944686026807,
      "price_change_24h": -53.41,
      "tx_volume_u_24h": 1940025.335991,
      "holders": 2000,
      "market_cap": "293789.5793414168904547727900463",
      "fdv": "293789.5793414168904547727900463",
      "risk_score": "0"
    },
    {
      "token": "A8C3xuqscfmyLrte3VmTqrAq8kgMASius9AFNANwpump",
      "chain": "solana",
      "symbol": "FWOG",
      "name": "FWOG",
      "logo_url": "https://www.iconaves.com/token_icon/solana/A8C3xuqscfmyLrte3VmTqrAq8kgMASius9AFNANwpump.png",
      "current_price_usd": 0.042708254879257224,
      "price_change_24h": 9.43,
      "tx_volume_u_24h": 1939886.791695,
      "holders": 79823,
      "market_cap": "41667023.253862398526996088041872",
      "fdv": "41667023.253862398526996088041872",
      "risk_score": "40"
    },
    {
      "token": "7x8woN8762h8ZBYqJkf4rrvr43eyJS2tVaWbSLKvpump",
      "chain": "solana",
      "symbol": "GAMES",
      "name": "GAMES",
      "logo_url": "https://www.iconaves.com/ipfs/pump/7x8woN8762h8ZBYqJkf4rrvr43eyJS2tVaWbSLKvpump_147.webp",
      "current_price_usd": 0.00013651806175550498,
      "price_change_24h": 110.67,
      "tx_volume_u_24h": 1773392.0924251908,
      "holders": 1253,
      "market_cap": "136518.06175550498000000000",
      "fdv": "136518.06175550498000000000",
      "risk_score": "0"
    },
    {
      "token": "Hax9LTgsQkze1YFychnBLtFH8gYbQKtKfWKKg2SP6gdD",
      "chain": "solana",
      "symbol": "TAI",
      "name": "TAI",
      "logo_url": "",
      "current_price_usd": 0.0637001211505072,
      "price_change_24h": -13.85,
      "tx_volume_u_24h": 1674290.980763,
      "holders": 75075,
      "market_cap": "57011074.9884641626958861938614432",
      "fdv": "57011074.9884641626958861938614432",
      "risk_score": "55"
    },
    {
      "token": "BQX1cjcRHXmrqNtoFWwmE5bZj7RPneTmqXB979b2pump",
      "chain": "solana",
      "symbol": "Italianrot",
      "name": "Italianrot",
      "logo_url": "https://www.iconaves.com/ipfs/pump/BQX1cjcRHXmrqNtoFWwmE5bZj7RPneTmqXB979b2pump.png",
      "current_price_usd": 0.007641911327351437,
      "price_change_24h": -10.64,
      "tx_volume_u_24h": 1621252.286025,
      "holders": 7126,
      "market_cap": "7641039.038040824760763120785235",
      "fdv": "7641039.038040824760763120785235",
      "risk_score": "40"
    },
    {
      "token": "KENJSUYLASHUMfHyy5o4Hp2FdNqZg1AsUPhfH2kYvEP",
      "chain": "solana",
      "symbol": "GRIFFAIN",
      "name": "GRIFFAIN",
      "logo_url": "https://www.iconaves.com/token_icon_solana/solana/KENJSUYLASHUMfHyy5o4Hp2FdNqZg1AsUPhfH2kYvEP.png",
      "current_price_usd": 0.05630335829975313,
      "price_change_24h": 3.76,
      "tx_volume_u_24h": 1585657.783163,
      "holders": 68868,
      "market_cap": "56295912.58143984998039274012297",
      "fdv": "56295912.58143984998039274012297",
      "risk_score": "40"
    },
    {
      "token": "HNg5PYJmtqcmzXrv6S9zP1CDKk5BgDuyFBxbvNApump",
      "chain": "solana",
      "symbol": "ALCH",
      "name": "ALCH",
      "logo_url": "https://www.iconaves.com/token_icon_solana/solana/HNg5PYJmtqcmzXrv6S9zP1CDKk5BgDuyFBxbvNApump.png",
      "current_price_usd": 0.17205301187682145,
      "price_change_24h": -3.01,
      "tx_volume_u_24h": 1582621.683788,
      "holders": 33057,
      "market_cap": "172050580.56170692163381444272925",
      "fdv": "172050580.56170692163381444272925",
      "risk_score": "40"
    },
    {
      "token": "3psH1Mj1f7yUfaD5gh6Zj7epE8hhrMkMETgv5TshQA4o",
      "chain": "solana",
      "symbol": "boden",
      "name": "boden",
      "logo_url": "https://www.iconaves.com/token_icon_solana/solana/3psH1Mj1f7yUfaD5gh6Zj7epE8hhrMkMETgv5TshQA4o.png",
      "current_price_usd": 0.0028053354462959533,
      "price_change_24h": 38.5,
      "tx_volume_u_24h": 1544585.56725,
      "holders": 26138,
      "market_cap": "1935991.5031824461529222655742812103",
      "fdv": "1935991.5031824461529222655742812103",
      "risk_score": "40"
    },
    {
      "token": "7xHWCekLSvehmYji5FXEWMNB6AfVpn5mqAKX6LUpump",
      "chain": "solana",
      "symbol": "urdad",
      "name": "urdad",
      "logo_url": "",
      "current_price_usd": 0.00007075646242011195,
      "price_change_24h": -36.72,
      "tx_volume_u_24h": 1477968.811856,
      "holders": 1651,
      "market_cap": "70756.46242011195000000000",
      "fdv": "70756.46242011195000000000",
      "risk_score": "0"
    },
    {
      "token": "Ai3eKAWjzKMV8wRwd41nVP83yqfbAVJykhvJVPxspump",
      "chain": "solana",
      "symbol": "moonpig",
      "name": "moonpig",
      "logo_url": "https://www.iconaves.com/ipfs/pump/Ai3eKAWjzKMV8wRwd41nVP83yqfbAVJykhvJVPxspump_147.webp",
      "current_price_usd": 0.007294269704349307,
      "price_change_24h": 15.78,
      "tx_volume_u_24h": 1323548.687161,
      "holders": 1617,
      "market_cap": "7293768.448341961972672011422142",
      "fdv": "7293768.448341961972672011422142",
      "risk_score": "0"
    },
    {
      "token": "74SBV4zDXxTRgv1pEMoECskKBkZHc2yGPnc7GYVepump",
      "chain": "solana",
      "symbol": "swarms",
      "name": "swarms",
      "logo_url": "https://www.iconaves.com/ipfs/pump/74SBV4zDXxTRgv1pEMoECskKBkZHc2yGPnc7GYVepump.png",
      "current_price_usd": 0.02356950108967665,
      "price_change_24h": 5.59,
      "tx_volume_u_24h": 1318617.621362,
      "holders": 39829,
      "market_cap": "23569040.9002610075538769772985",
      "fdv": "23569040.9002610075538769772985",
      "risk_score": "40"
    },
    {
      "token": "3pA668WX5vNjQMw2KdHJ8RpZceG6gEfXWtRvGChjbSnz",
      "chain": "solana",
      "symbol": "ANIME",
      "name": "ANIME",
      "logo_url": "https://www.iconaves.com/ipfs/pump/3pA668WX5vNjQMw2KdHJ8RpZceG6gEfXWtRvGChjbSnz_147.webp",
      "current_price_usd": 0.0005802773647310294,
      "price_change_24h": -21.94,
      "tx_volume_u_24h": 1283640.679931,
      "holders": 2059,
      "market_cap": "580267.7011582202747241576869828",
      "fdv": "580267.7011582202747241576869828",
      "risk_score": "40"
    },
    {
      "token": "9zNQRsGLjNKwCUU5Gq5LR8beUCPzQMVMqKAi3SSZh54u",
      "chain": "solana",
      "symbol": "FDUSD",
      "name": "FDUSD",
      "logo_url": "https://www.iconaves.com/token_icon/solana/9zNQRsGLjNKwCUU5Gq5LR8beUCPzQMVMqKAi3SSZh54u.png",
      "current_price_usd": 0.9984012168192968,
      "price_change_24h": -0.08,
      "tx_volume_u_24h": 1211013.4859228083,
      "holders": 2988,
      "market_cap": "103839050.9217121947900659465072",
      "fdv": "103839050.9217121947900659465072",
      "risk_score": "20"
    },
    {
      "token": "CniPCE4b3s8gSUPhUiyMjXnytrEqUrMfSsnbBjLCpump",
      "chain": "solana",
      "symbol": "pwease",
      "name": "pwease",
      "logo_url": "https://www.iconaves.com/ipfs/pump/CniPCE4b3s8gSUPhUiyMjXnytrEqUrMfSsnbBjLCpump.png",
      "current_price_usd": 0.004987891928560371,
      "price_change_24h": 15.39,
      "tx_volume_u_24h": 1142148.785739,
      "holders": 21781,
      "market_cap": "4987444.873207903058843143174122",
      "fdv": "4987444.873207903058843143174122",
      "risk_score": "40"
    },
    {
      "token": "9Wkcek2EZFmJf5L2XmC5rfnNVBrdndbMe6yW8fbfbonk",
      "chain": "solana",
      "symbol": "CHACHA",
      "name": "CHACHA",
      "logo_url": "https://www.iconaves.com/ipfs/bonk/9Wkcek2EZFmJf5L2XmC5rfnNVBrdndbMe6yW8fbfbonk_147_20250430141249.webp",
      "current_price_usd": 0.0014953384593113582,
      "price_change_24h": -30.58,
      "tx_volume_u_24h": 1140779.420688,
      "holders": 2279,
      "market_cap": "1495312.4564370078087923137501208",
      "fdv": "1495312.4564370078087923137501208",
      "risk_score": "40"
    },
    {
      "token": "61V8vBaqAGMpgDQi4JcAwo1dmBGHsyhzodcPqnEVpump",
      "chain": "solana",
      "symbol": "arc",
      "name": "arc",
      "logo_url": "https://www.iconaves.com/token_icon_solana/solana/61V8vBaqAGMpgDQi4JcAwo1dmBGHsyhzodcPqnEVpump.png",
      "current_price_usd": 0.054152999082119346,
      "price_change_24h": 1.18,
      "tx_volume_u_24h": 1083658.3374082278,
      "holders": 53907,
      "market_cap": "54152675.938712784681074099530632",
      "fdv": "54152675.938712784681074099530632",
      "risk_score": "40"
    },
    {
      "token": "D8RaN4ZXKkemC7pyu2noMB8n6ptDPkzuMFp4KfZSpkin",
      "chain": "solana",
      "symbol": "TED",
      "name": "TED",
      "logo_url": "",
      "current_price_usd": 0.03609487883371745,
      "price_change_24h": 118.98,
      "tx_volume_u_24h": 1075726.743198,
      "holders": 1076,
      "market_cap": "36094878.83368330424462330329230",
      "fdv": "36094878.83368330424462330329230",
      "risk_score": "55"
    },
    {
      "token": "BpRMSjbQqm26f51HYKeBLfKEs43yXUhaKA8DXvCxpump",
      "chain": "solana",
      "symbol": "fried",
      "name": "fried",
      "logo_url": "https://www.iconaves.com/ipfs/pump/BpRMSjbQqm26f51HYKeBLfKEs43yXUhaKA8DXvCxpump.png",
      "current_price_usd": 0.0005047427142531472,
      "price_change_24h": -1.8,
      "tx_volume_u_24h": 1023064.515907,
      "holders": 1573,
      "market_cap": "504138.65989271656462961968096",
      "fdv": "504138.65989271656462961968096",
      "risk_score": "0"
    },
    {
      "token": "ukHH6c7mMyiWCf1b9pnWe25TSpkDDt3H5pQZgZ74J82",
      "chain": "solana",
      "symbol": "BOME",
      "name": "BOME",
      "logo_url": "https://www.iconaves.com/token_icon_solana/solana/ukHH6c7mMyiWCf1b9pnWe25TSpkDDt3H5pQZgZ74J82.png",
      "current_price_usd": 0.0013852265273191688,
      "price_change_24h": 1.86,
      "tx_volume_u_24h": 996477.5509293808,
      "holders": 86842,
      "market_cap": "95486539.1359341646314317042000544",
      "fdv": "95486539.1359341646314317042000544",
      "risk_score": "20"
    },
    {
      "token": "63LfDmNb3MQ8mw9MtZ2To9bEA2M71kZUUGq5tiJxcqj9",
      "chain": "solana",
      "symbol": "GIGA",
      "name": "GIGA",
      "logo_url": "https://www.iconaves.com/token_icon_solana/solana/63LfDmNb3MQ8mw9MtZ2To9bEA2M71kZUUGq5tiJxcqj9_20240710100933.png",
      "current_price_usd": 0.016918083463335388,
      "price_change_24h": 0.8,
      "tx_volume_u_24h": 970224.356441,
      "holders": 83447,
      "market_cap": "162479569.44226661410057852698928",
      "fdv": "162479569.44226661410057852698928",
      "risk_score": "40"
    },
    {
      "token": "C7heQqfNzdMbUFQwcHkL9FvdwsFsDRBnfwZDDyWYCLTZ",
      "chain": "solana",
      "symbol": "$COLLAT",
      "name": "$COLLAT",
      "logo_url": "https://www.iconaves.com/token_icon_solana/solana/C7heQqfNzdMbUFQwcHkL9FvdwsFsDRBnfwZDDyWYCLTZ.png",
      "current_price_usd": 0.012588877720402404,
      "price_change_24h": 20.94,
      "tx_volume_u_24h": 963305.732045,
      "holders": 9818,
      "market_cap": "12588389.968645269196135233874308",
      "fdv": "12588389.968645269196135233874308",
      "risk_score": "40"
    },
    {
      "token": "5z3EqYQo9HiCEs3R84RCDMu2n7anpDMxRhdK8PSWmrRC",
      "chain": "solana",
      "symbol": "PONKE",
      "name": "PONKE",
      "logo_url": "https://www.iconaves.com/token_icon_solana/solana/5z3EqYQo9HiCEs3R84RCDMu2n7anpDMxRhdK8PSWmrRC.png",
      "current_price_usd": 0.11800076920005344,
      "price_change_24h": 14.84,
      "tx_volume_u_24h": 959313.860164,
      "holders": 75770,
      "market_cap": "65554086.69723452789266448895759424",
      "fdv": "65554086.69723452789266448895759424",
      "risk_score": "40"
    },
    {
      "token": "FasH397CeZLNYWkd3wWK9vrmjd1z93n3b59DssRXpump",
      "chain": "solana",
      "symbol": "BUTTCOIN",
      "name": "BUTTCOIN",
      "logo_url": "https://www.iconaves.com/ipfs/pump/FasH397CeZLNYWkd3wWK9vrmjd1z93n3b59DssRXpump.png",
      "current_price_usd": 0.003726106541789101,
      "price_change_24h": -1.9,
      "tx_volume_u_24h": 935270.308897,
      "holders": 15767,
      "market_cap": "3721945.391204497924131093559463",
      "fdv": "3721945.391204497924131093559463",
      "risk_score": "40"
    },
    {
      "token": "JosjEXh69RckgSs2AWsN1xN8zmiSHxBuJjHLURJnHhg",
      "chain": "solana",
      "symbol": "JOS",
      "name": "JOS",
      "logo_url": "",
      "current_price_usd": 0.008095685105323571,
      "price_change_24h": -11.12,
      "tx_volume_u_24h": 857939.375911,
      "holders": 4336,
      "market_cap": "8095636.858101491819226893990091",
      "fdv": "8095636.858101491819226893990091",
      "risk_score": "40"
    },
    {
      "token": "5mbK36SZ7J19An8jFochhQS4of8g6BwUjbeCSxBSoWdp",
      "chain": "solana",
      "symbol": "$michi",
      "name": "$michi",
      "logo_url": "https://www.iconaves.com/token_icon_solana/solana/5mbK36SZ7J19An8jFochhQS4of8g6BwUjbeCSxBSoWdp.png",
      "current_price_usd": 0.030162455234754075,
      "price_change_24h": 5.18,
      "tx_volume_u_24h": 848129.989597,
      "holders": 48103,
      "market_cap": "16763235.433501039486793275216950",
      "fdv": "16763235.433501039486793275216950",
      "risk_score": "40"
    },
    {
      "token": "2wzVMXhLypmP92mXNCq4fuFcd9TCC972AbMfuiH3pump",
      "chain": "solana",
      "symbol": "AISLOP",
      "name": "AISLOP",
      "logo_url": "https://www.iconaves.com/ipfs/pump/2wzVMXhLypmP92mXNCq4fuFcd9TCC972AbMfuiH3pump.png",
      "current_price_usd": 0.0022014950225220102,
      "price_change_24h": 45.66,
      "tx_volume_u_24h": 828929.675422,
      "holders": 1465,
      "market_cap": "2201314.7002492457240229735893988",
      "fdv": "2201314.7002492457240229735893988",
      "risk_score": "40"
    },
    {
      "token": "SonicxvLud67EceaEzCLRnMTBqzYUUYNr93DBkBdDES",
      "chain": "solana",
      "symbol": "SONIC",
      "name": "SONIC",
      "logo_url": "https://www.iconaves.com/token_icon_solana/solana/SonicxvLud67EceaEzCLRnMTBqzYUUYNr93DBkBdDES.png",
      "current_price_usd": 0.28711409259288223,
      "price_change_24h": 8.28,
      "tx_volume_u_24h": 825056.11672,
      "holders": 45375,
      "market_cap": "689073632.25423813350111369862555172",
      "fdv": "689073632.25423813350111369862555172",
      "risk_score": "55"
    },
    {
      "token": "DBRiDgJAMsM95moTzJs7M9LnkGErpbv9v6CUR1DXnUu5",
      "chain": "solana",
      "symbol": "DBR",
      "name": "DBR",
      "logo_url": "https://www.iconaves.com/token_icon_solana/solana/DBRiDgJAMsM95moTzJs7M9LnkGErpbv9v6CUR1DXnUu5.png",
      "current_price_usd": 0.017389211759327557,
      "price_change_24h": 6.53,
      "tx_volume_u_24h": 821272.978539,
      "holders": 107851,
      "market_cap": "173891755.987403116902319886854983",
      "fdv": "173891755.987403116902319886854983",
      "risk_score": "55"
    },
    {
      "token": "8cw814BPZVxwMrreFcESBwyQJanfEXBZawihNBtPpump",
      "chain": "solana",
      "symbol": "Gorkxbt",
      "name": "Gorkxbt",
      "logo_url": "https://www.iconaves.com/ipfs/pump/8cw814BPZVxwMrreFcESBwyQJanfEXBZawihNBtPpump_147.webp",
      "current_price_usd": 0.00015221500967538444,
      "price_change_24h": 152.45,
      "tx_volume_u_24h": 789077.78652,
      "holders": 1164,
      "market_cap": "152215.00967538444000000000",
      "fdv": "152215.00967538444000000000",
      "risk_score": "0"
    },
    {
      "token": "F83qesR5cuCkc4ZgdeLsTQorHhE4xKHYMV4Uj69Upump",
      "chain": "solana",
      "symbol": "memesexual",
      "name": "memesexual",
      "logo_url": "https://www.iconaves.com/ipfs/pump/F83qesR5cuCkc4ZgdeLsTQorHhE4xKHYMV4Uj69Upump_147.webp",
      "current_price_usd": 0.00007054658201331913,
      "price_change_24h": -36.89,
      "tx_volume_u_24h": 783145.259204,
      "holders": 1216,
      "market_cap": "70546.58201331913000000000",
      "fdv": "70546.58201331913000000000",
      "risk_score": "0"
    },
    {
      "token": "CBdCxKo9QavR9hfShgpEBG3zekorAeD7W1jfq2o3pump",
      "chain": "solana",
      "symbol": "LUCE",
      "name": "LUCE",
      "logo_url": "https://www.iconaves.com/token_icon_request/6720e9bb728dd5069f2246fb_1730210577.png",
      "current_price_usd": 0.009603093919600961,
      "price_change_24h": 1.23,
      "tx_volume_u_24h": 777828.992196,
      "holders": 43833,
      "market_cap": "9602918.228759912130521732260092",
      "fdv": "9602918.228759912130521732260092",
      "risk_score": "40"
    },
    {
      "token": "2qEHjDLDLbuBgRYvsxhc5D6uDWAivNFZGan56P1tpump",
      "chain": "solana",
      "symbol": "Pnut",
      "name": "Pnut",
      "logo_url": "https://www.iconaves.com/token_icon_request/6726a098b2402d7b98c12fde_1730594088.png",
      "current_price_usd": 0.15753655522288706,
      "price_change_24h": 1.57,
      "tx_volume_u_24h": 770247.8944066342,
      "holders": 88168,
      "market_cap": "157513376.72237986448734836060472",
      "fdv": "157513376.72237986448734836060472",
      "risk_score": "40"
    },
    {
      "token": "RhFVq1Zt81VvcoSEMSyCGZZv5SwBdA8MV7w4HEMpump",
      "chain": "solana",
      "symbol": "CFX",
      "name": "CFX",
      "logo_url": "https://www.iconaves.com/ipfs/pump/RhFVq1Zt81VvcoSEMSyCGZZv5SwBdA8MV7w4HEMpump.png",
      "current_price_usd": 0.0010742648431918587,
      "price_change_24h": -25.41,
      "tx_volume_u_24h": 763549.541466,
      "holders": 2697,
      "market_cap": "1074220.3178434621137903889368015",
      "fdv": "1074220.3178434621137903889368015",
      "risk_score": "0"
    },
    {
      "token": "eL5fUxj2J4CiQsmW85k5FG9DvuQjjUoBHoQBi2Kpump",
      "chain": "solana",
      "symbol": "UFD",
      "name": "Unicorn Fart Dust",
      "logo_url": "https://www.iconaves.com/token_icon_solana/solana/eL5fUxj2J4CiQsmW85k5FG9DvuQjjUoBHoQBi2Kpump.png",
      "current_price_usd": 0.022763496337572145,
      "price_change_24h": 9.91,
      "tx_volume_u_24h": 758055.006211,
      "holders": 38578,
      "market_cap": "22763009.194989058057780241188055",
      "fdv": "22763009.194989058057780241188055",
      "risk_score": "40"
    },
    {
      "token": "AfyDiEptGHEDgD69y56XjNSbTs23LaF1YHANVKnWpump",
      "chain": "solana",
      "symbol": "TKNZ",
      "name": "TKNZ",
      "logo_url": "https://www.iconaves.com/ipfs/pump/AfyDiEptGHEDgD69y56XjNSbTs23LaF1YHANVKnWpump_147.webp",
      "current_price_usd": 0.0011160976685844117,
      "price_change_24h": -16.66,
      "tx_volume_u_24h": 727545.1789065953,
      "holders": 1109,
      "market_cap": "1116076.4047398530617548182763219",
      "fdv": "1116076.4047398530617548182763219",
      "risk_score": "0"
    },
    {
      "token": "ArUyEVWGCzZMtAxcPmNH8nDFZ4kMjxrMbpsQf3NEpump",
      "chain": "solana",
      "symbol": "BAYC",
      "name": "BAYC",
      "logo_url": "https://www.iconaves.com/token_icon_request/681b14fe00db497da7028edd_1746605310.png",
      "current_price_usd": 0.11060411383416081,
      "price_change_24h": 1.73,
      "tx_volume_u_24h": 727127.97106,
      "holders": 6537,
      "market_cap": "110604113.83416081000000000",
      "fdv": "110604113.83416081000000000",
      "risk_score": "40"
    },
    {
      "token": "7D1iYWfhw2cr9yBZBFE6nZaaSUvXHqG5FizFFEZwpump",
      "chain": "solana",
      "symbol": "YNE",
      "name": "YNE",
      "logo_url": "https://www.iconaves.com/ipfs/pump/7D1iYWfhw2cr9yBZBFE6nZaaSUvXHqG5FizFFEZwpump.png",
      "current_price_usd": 0.005655292567408854,
      "price_change_24h": 6.91,
      "tx_volume_u_24h": 714216.340602,
      "holders": 13270,
      "market_cap": "5655237.568484516710734724215174",
      "fdv": "5655237.568484516710734724215174",
      "risk_score": "40"
    },
    {
      "token": "6AJcP7wuLwmRYLBNbi825wgguaPsWzPBEHcHndpRpump",
      "chain": "solana",
      "symbol": "VINE",
      "name": "Vine Coin",
      "logo_url": "https://www.iconaves.com/token_icon_solana/solana/6AJcP7wuLwmRYLBNbi825wgguaPsWzPBEHcHndpRpump.png",
      "current_price_usd": 0.03653885811248161,
      "price_change_24h": 3.25,
      "tx_volume_u_24h": 713869.093791,
      "holders": 108568,
      "market_cap": "36538259.86911136222802695642055",
      "fdv": "36538259.86911136222802695642055",
      "risk_score": "40"
    },
    {
      "token": "Cy1GS2FqefgaMbi45UunrUzin1rfEmTUYnomddzBpump",
      "chain": "solana",
      "symbol": "MOBY",
      "name": "MOBY",
      "logo_url": "https://www.iconaves.com/ipfs/pump/Cy1GS2FqefgaMbi45UunrUzin1rfEmTUYnomddzBpump.png",
      "current_price_usd": 0.012649177180584276,
      "price_change_24h": 9,
      "tx_volume_u_24h": 713748.555523,
      "holders": 24287,
      "market_cap": "12648836.1073118995950202636596",
      "fdv": "12648836.1073118995950202636596",
      "risk_score": "40"
    },
    {
      "token": "Hjw6bEcHtbHGpQr8onG3izfJY5DJiWdt7uk2BfdSpump",
      "chain": "solana",
      "symbol": "SNAI",
      "name": "SNAI",
      "logo_url": "https://www.iconaves.com/ipfs/pump/Hjw6bEcHtbHGpQr8onG3izfJY5DJiWdt7uk2BfdSpump.png",
      "current_price_usd": 0.015097716165200229,
      "price_change_24h": 8.41,
      "tx_volume_u_24h": 683616.96131,
      "holders": 33294,
      "market_cap": "15097282.668029013737278284091944",
      "fdv": "15097282.668029013737278284091944",
      "risk_score": "40"
    },
    {
      "token": "Cz75ZtjwgZmr5J1VDBRTm5ZybZvEFR5DEdb8hEy59pWq",
      "chain": "solana",
      "symbol": "FUCKCOIN",
      "name": "FUCKCOIN",
      "logo_url": "",
      "current_price_usd": 0.0006952290451270585,
      "price_change_24h": -46.67,
      "tx_volume_u_24h": 676867.813445,
      "holders": 3073,
      "market_cap": "695213.1906186550187828311080665",
      "fdv": "695213.1906186550187828311080665",
      "risk_score": "55"
    },
    {
      "token": "Dfh5DzRgSvvCFDoYc2ciTkMrbDfRKybA4SoFbPmApump",
      "chain": "solana",
      "symbol": "pippin",
      "name": "Pippin",
      "logo_url": "https://www.iconaves.com/token_icon/solana/Dfh5DzRgSvvCFDoYc2ciTkMrbDfRKybA4SoFbPmApump.png",
      "current_price_usd": 0.016433216971744668,
      "price_change_24h": -1.65,
      "tx_volume_u_24h": 660041.153722639,
      "holders": 28433,
      "market_cap": "16432329.27501331239904287015444",
      "fdv": "16432329.27501331239904287015444",
      "risk_score": "40"
    },
    {
      "token": "7C5SPivzYtk2umHScjLXN7WZnstLFf1r5TCsMNaTpump",
      "chain": "solana",
      "symbol": "BRUTE",
      "name": "BRUTE",
      "logo_url": "https://www.iconaves.com/ipfs/pump/7C5SPivzYtk2umHScjLXN7WZnstLFf1r5TCsMNaTpump_147.webp",
      "current_price_usd": 0.0003944331883575696,
      "price_change_24h": 67.59,
      "tx_volume_u_24h": 656692.1174,
      "holders": 1016,
      "market_cap": "394433.1883575696000000000",
      "fdv": "394433.1883575696000000000",
      "risk_score": "0"
    },
    {
      "token": "2z1p8xCEjRzpBHjXWrx4tJnz7BFL6z7NnvbCxH7bpump",
      "chain": "solana",
      "symbol": "San",
      "name": "San",
      "logo_url": "https://www.iconaves.com/ipfs/pump/2z1p8xCEjRzpBHjXWrx4tJnz7BFL6z7NnvbCxH7bpump.png",
      "current_price_usd": 0.00887469904787185,
      "price_change_24h": -21.57,
      "tx_volume_u_24h": 655332.5307217991,
      "holders": 5481,
      "market_cap": "8359690.26206250673841226853275",
      "fdv": "8359690.26206250673841226853275",
      "risk_score": "40"
    },
    {
      "token": "ZBCNpuD7YMXzTHB2fhGkGi78MNsHGLRXUhRewNRm9RU",
      "chain": "solana",
      "symbol": "ZBCN",
      "name": "ZBCN",
      "logo_url": "https://www.iconaves.com/token_icon_solana/solana/ZBCNpuD7YMXzTHB2fhGkGi78MNsHGLRXUhRewNRm9RU.png",
      "current_price_usd": 0.0017412562068965518,
      "price_change_24h": -8.59,
      "tx_volume_u_24h": 646515.787238,
      "holders": 49708,
      "market_cap": "174124544.1171597992300037861515022",
      "fdv": "174124544.1171597992300037861515022",
      "risk_score": "55"
    },
    {
      "token": "HtrvP4fG9KiFqFeu4f32RuZiwG3nmYwPkPZ61nAbpump",
      "chain": "solana",
      "symbol": "PHARMA",
      "name": "PHARMA",
      "logo_url": "https://www.iconaves.com/ipfs/pump/HtrvP4fG9KiFqFeu4f32RuZiwG3nmYwPkPZ61nAbpump.png",
      "current_price_usd": 0.0020948758087105867,
      "price_change_24h": 14.48,
      "tx_volume_u_24h": 639298.196871,
      "holders": 1214,
      "market_cap": "2094864.8500364694092028633822932",
      "fdv": "2094864.8500364694092028633822932",
      "risk_score": "0"
    },
    {
      "token": "5241BVJpTDscdFM5bTmeuchBcjXN5sasBywyF7onkJZP",
      "chain": "solana",
      "symbol": "PUFF",
      "name": "PUFF",
      "logo_url": "https://www.iconaves.com/ipfs/pump/5241BVJpTDscdFM5bTmeuchBcjXN5sasBywyF7onkJZP.png",
      "current_price_usd": 0.004692518499105886,
      "price_change_24h": 15.43,
      "tx_volume_u_24h": 638886.021107,
      "holders": 1850,
      "market_cap": "4692513.887464228976272700222764",
      "fdv": "4692513.887464228976272700222764",
      "risk_score": "40"
    },
    {
      "token": "BYZ9CcZGKAXmN2uDsKcQMM9UnZacija4vWcns9Th69xb",
      "chain": "solana",
      "symbol": "BOTIFY",
      "name": "BOTIFY",
      "logo_url": "https://www.iconaves.com/token_icon_request/6781b25a3ed504797607bdb3_1736553051.png",
      "current_price_usd": 0.011790695206009344,
      "price_change_24h": -7.9,
      "tx_volume_u_24h": 632706.2555028131,
      "holders": 17798,
      "market_cap": "11790270.376330554655385541682176",
      "fdv": "11790270.376330554655385541682176",
      "risk_score": "40"
    },
    {
      "token": "ED5nyyWEzpPPiWimP8vYm7sD7TD3LAt3Q3gRTWHzPJBY",
      "chain": "solana",
      "symbol": "MOODENG",
      "name": "MOODENG",
      "logo_url": "https://www.iconaves.com/token_icon/solana/ED5nyyWEzpPPiWimP8vYm7sD7TD3LAt3Q3gRTWHzPJBY.png",
      "current_price_usd": 0.03965843656586649,
      "price_change_24h": 5.02,
      "tx_volume_u_24h": 626392.067986,
      "holders": 68752,
      "market_cap": "39259523.10741134178873346848015",
      "fdv": "39259523.10741134178873346848015",
      "risk_score": "20"
    },
    {
      "token": "AxriehR6Xw3adzHopnvMn7GcpRFcD41ddpiTWMg6pump",
      "chain": "solana",
      "symbol": "jailstool",
      "name": "jailstool",
      "logo_url": "https://www.iconaves.com/ipfs/pump/AxriehR6Xw3adzHopnvMn7GcpRFcD41ddpiTWMg6pump.png",
      "current_price_usd": 0.0040110177561303115,
      "price_change_24h": -15.32,
      "tx_volume_u_24h": 606086.369272,
      "holders": 63649,
      "market_cap": "4010272.1253225796006925088395985",
      "fdv": "4010272.1253225796006925088395985",
      "risk_score": "40"
    },
    {
      "token": "5tmsiuCDPdjq4nA4GVjAgayL7ehgGPJ47mNmNvBboop",
      "chain": "solana",
      "symbol": "Beevo",
      "name": "Beevo",
      "logo_url": "https://www.iconaves.com/token_icon_request/681a79c92677b7c10ff48bb6_1746565578.png",
      "current_price_usd": 0.0009508944421674388,
      "price_change_24h": -6.67,
      "tx_volume_u_24h": 597522.406359,
      "holders": 1192,
      "market_cap": "950894.4421674388000000000",
      "fdv": "950894.4421674388000000000",
      "risk_score": "40"
    },
    {
      "token": "CzLSujWBLFsSjncfkh59rUFqvafWcY5tzedWJSuypump",
      "chain": "solana",
      "symbol": "GOAT",
      "name": "GOAT",
      "logo_url": "https://www.iconaves.com/token_icon_request/671fdea1f8d9f7a5f53fdfe7_1730144315.png",
      "current_price_usd": 0.07239134775339065,
      "price_change_24h": 3.75,
      "tx_volume_u_24h": 596024.1947188481,
      "holders": 88529,
      "market_cap": "72390867.30511496990492749489880",
      "fdv": "72390867.30511496990492749489880",
      "risk_score": "50"
    },
    {
      "token": "CDBdbNqmrLu1PcgjrFG52yxg71QnFhBZcUE6PSFdbonk",
      "chain": "solana",
      "symbol": "LetsBONK",
      "name": "LetsBONK",
      "logo_url": "https://www.iconaves.com/ipfs/bonk/CDBdbNqmrLu1PcgjrFG52yxg71QnFhBZcUE6PSFdbonk.png",
      "current_price_usd": 0.018638186223192462,
      "price_change_24h": 6.15,
      "tx_volume_u_24h": 575835.786827,
      "holders": 7898,
      "market_cap": "1286022.253057611963939565080822",
      "fdv": "1286022.253057611963939565080822",
      "risk_score": "40"
    },
    {
      "token": "6c9kxpL8F99tY5cJcfreSYojLEuwVvicpww1HbvCpump",
      "chain": "solana",
      "symbol": "FAGS",
      "name": "FAGS",
      "logo_url": "https://www.iconaves.com/ipfs/pump/6c9kxpL8F99tY5cJcfreSYojLEuwVvicpww1HbvCpump_147.webp",
      "current_price_usd": 0.0000683645126777768,
      "price_change_24h": -46.42,
      "tx_volume_u_24h": 524371.031434,
      "holders": 1910,
      "market_cap": "68364.5126777768000000000",
      "fdv": "68364.5126777768000000000",
      "risk_score": "0"
    },
    {
      "token": "FWAr6oWa6CHg6WUcXu8CqkmsdbhtEqL8t31QTonppump",
      "chain": "solana",
      "symbol": "PVS",
      "name": "PVS",
      "logo_url": "https://www.iconaves.com/ipfs/pump/FWAr6oWa6CHg6WUcXu8CqkmsdbhtEqL8t31QTonppump.png",
      "current_price_usd": 0.006872281282478711,
      "price_change_24h": 0.69,
      "tx_volume_u_24h": 516174.35356,
      "holders": 6639,
      "market_cap": "6871223.143251346591988894357707",
      "fdv": "6871223.143251346591988894357707",
      "risk_score": "40"
    },
    {
      "token": "GJtJuWD9qYcCkrwMBmtY1tpapV1sKfB2zUv9Q4aqpump",
      "chain": "solana",
      "symbol": "$RIF",
      "name": "$RIF",
      "logo_url": "https://www.iconaves.com/token_icon_solana/solana/GJtJuWD9qYcCkrwMBmtY1tpapV1sKfB2zUv9Q4aqpump.png",
      "current_price_usd": 0.002178795562509694,
      "price_change_24h": -15.92,
      "tx_volume_u_24h": 510887.41047,
      "holders": 34888,
      "market_cap": "2177977.805125953321626083581398",
      "fdv": "2177977.805125953321626083581398",
      "risk_score": "40"
    },
    {
      "token": "81YHAzq9yfptVbNTHiYuMVKVQ6ZNs3XeQFFENnNUpump",
      "chain": "solana",
      "symbol": "DMCP",
      "name": "DMCP",
      "logo_url": "https://www.iconaves.com/ipfs/pump/81YHAzq9yfptVbNTHiYuMVKVQ6ZNs3XeQFFENnNUpump.png",
      "current_price_usd": 0.002078992101339005,
      "price_change_24h": -45.62,
      "tx_volume_u_24h": 510310.475417,
      "holders": 5447,
      "market_cap": "2078989.526313122103329852467030",
      "fdv": "2078989.526313122103329852467030",
      "risk_score": "0"
    },
    {
      "token": "6NcdiK8B5KK2DzKvzvCfqi8EHaEqu48fyEzC8Mm9pump",
      "chain": "solana",
      "symbol": "STONKS",
      "name": "STONKS",
      "logo_url": "https://www.logofacade.com/ipfs/pump/6NcdiK8B5KK2DzKvzvCfqi8EHaEqu48fyEzC8Mm9pump.png",
      "current_price_usd": 0.04289709904622301,
      "price_change_24h": 3.1,
      "tx_volume_u_24h": 509990.3554293207,
      "holders": 15793,
      "market_cap": "42894297.95931866227022930762343",
      "fdv": "42894297.95931866227022930762343",
      "risk_score": "40"
    },
    {
      "token": "2tbHkvuJnaG1X2U4VXvKTFsvaoW2cZ2W4iM9ZmdYmoon",
      "chain": "solana",
      "symbol": "JProof",
      "name": "JProof",
      "logo_url": "",
      "current_price_usd": 0.10418521149126297,
      "price_change_24h": 11.92,
      "tx_volume_u_24h": 509364.234974,
      "holders": 3859,
      "market_cap": "100978556.27141589462330043193520813",
      "fdv": "100978556.27141589462330043193520813",
      "risk_score": "55"
    },
    {
      "token": "14AALaZZowAceKjf7LuwLyGM2gSzkjPmyNUzW1asboop",
      "chain": "solana",
      "symbol": "gf",
      "name": "gf",
      "logo_url": "https://www.iconaves.com/boop/solana/14AALaZZowAceKjf7LuwLyGM2gSzkjPmyNUzW1asboop_147_20250505171203.webp",
      "current_price_usd": 0.0008957218998671911,
      "price_change_24h": 20.75,
      "tx_volume_u_24h": 505131.1581202547,
      "holders": 1085,
      "market_cap": "895721.8998671911000000000",
      "fdv": "895721.8998671911000000000",
      "risk_score": "40"
    },
    {
      "token": "7rnYT9QqS9RKYFJnDT14T14LxmG1c3xZo61pSVJRpump",
      "chain": "solana",
      "symbol": "POPE",
      "name": "POPE",
      "logo_url": "https://www.iconaves.com/ipfs/pump/7rnYT9QqS9RKYFJnDT14T14LxmG1c3xZo61pSVJRpump.png",
      "current_price_usd": 0.0008429737422833304,
      "price_change_24h": 66.01,
      "tx_volume_u_24h": 494273.653045,
      "holders": 1798,
      "market_cap": "842631.9918383956348803667842792",
      "fdv": "842631.9918383956348803667842792",
      "risk_score": "40"
    },
    {
      "token": "GekTNfm84QfyP2GdAHZ5AgACBRd69aNmgA5FDhZupump",
      "chain": "solana",
      "symbol": "GRIFT",
      "name": "ORBIT",
      "logo_url": "https://www.iconaves.com/token_icon_solana/solana/GekTNfm84QfyP2GdAHZ5AgACBRd69aNmgA5FDhZupump.png",
      "current_price_usd": 0.007936616638228212,
      "price_change_24h": -2,
      "tx_volume_u_24h": 484639.608217,
      "holders": 26835,
      "market_cap": "7936551.479823827244031042944516",
      "fdv": "7936551.479823827244031042944516",
      "risk_score": "40"
    },
    {
      "token": "5ycBARVYYau1CW8s1r6Ty439rbVvGm7x5DRkxGiGKmZ",
      "chain": "solana",
      "symbol": "JOEVER",
      "name": "JOEVER",
      "logo_url": "",
      "current_price_usd": 0.0044142011561797805,
      "price_change_24h": 56.58,
      "tx_volume_u_24h": 480267.410611,
      "holders": 3521,
      "market_cap": "42677.6578039136665940684267694105",
      "fdv": "42677.6578039136665940684267694105",
      "risk_score": "40"
    },
    {
      "token": "25Ew9oMprcypdK2KbecFE6Btvy5HChaDYUmLdm7aLinK",
      "chain": "solana",
      "symbol": "NATION",
      "name": "NATION",
      "logo_url": "https://www.iconaves.com/token_icon_request/6803a5e5f98642bfa630e2ce_1745069541.png",
      "current_price_usd": 0.0032667056489450704,
      "price_change_24h": 0.42,
      "tx_volume_u_24h": 453757.320821,
      "holders": 1089,
      "market_cap": "3266703.3732892393920061871449808",
      "fdv": "3266703.3732892393920061871449808",
      "risk_score": "55"
    },
    {
      "token": "HgBRWfYxEfvPhtqkaeymCQtHCrKE46qQ43pKe8HCpump",
      "chain": "solana",
      "symbol": "Bert",
      "name": "Bert",
      "logo_url": "https://www.iconaves.com/token_icon_solana/solana/HgBRWfYxEfvPhtqkaeymCQtHCrKE46qQ43pKe8HCpump.png",
      "current_price_usd": 0.017443995410143482,
      "price_change_24h": 18.78,
      "tx_volume_u_24h": 453392.964911,
      "holders": 22803,
      "market_cap": "17090456.694850100008107189667932",
      "fdv": "17090456.694850100008107189667932",
      "risk_score": "40"
    },
    {
      "token": "C29ebrgYjYoJPMGPnPSGY1q3mMGk4iDSqnQeQQA7moon",
      "chain": "solana",
      "symbol": "NOBODY",
      "name": "NOBODY",
      "logo_url": "https://www.iconaves.com/token_icon_solana/solana/C29ebrgYjYoJPMGPnPSGY1q3mMGk4iDSqnQeQQA7moon.png",
      "current_price_usd": 0.005166718154276997,
      "price_change_24h": 6.91,
      "tx_volume_u_24h": 439210.119575,
      "holders": 5079,
      "market_cap": "4867356.084861851020366610498807208",
      "fdv": "4867356.084861851020366610498807208",
      "risk_score": "40"
    },
    {
      "token": "HhJpBhRRn4g56VsyLuT8DL5Bv31HkXqsrahTTUCZeZg4",
      "chain": "solana",
      "symbol": "$MYRO",
      "name": "$MYRO",
      "logo_url": "https://www.iconaves.com/token_icon_solana/solana/HhJpBhRRn4g56VsyLuT8DL5Bv31HkXqsrahTTUCZeZg4.png",
      "current_price_usd": 0.023572449209481476,
      "price_change_24h": -3.36,
      "tx_volume_u_24h": 436090.611254,
      "holders": 52325,
      "market_cap": "23571600.802543877126857596201684016",
      "fdv": "23571600.802543877126857596201684016",
      "risk_score": "40"
    },
    {
      "token": "zDKuB27WrGGDUfAJ4ktmPAfCM6sfntMjrGhEva6pump",
      "chain": "solana",
      "symbol": "NINA",
      "name": "NINA",
      "logo_url": "https://www.iconaves.com/ipfs/pump/zDKuB27WrGGDUfAJ4ktmPAfCM6sfntMjrGhEva6pump_147.webp",
      "current_price_usd": 0.0018945084240574277,
      "price_change_24h": 44963.75,
      "tx_volume_u_24h": 432552.564564,
      "holders": 1124,
      "market_cap": "1894423.9206884908508542218412561",
      "fdv": "1894423.9206884908508542218412561",
      "risk_score": "0"
    },
    {
      "token": "Ey59PH7Z4BFU4HjyKnyMdWt5GGN76KazTAwQihoUXRnk",
      "chain": "solana",
      "symbol": "PASTERNAK",
      "name": "PASTERNAK",
      "logo_url": "",
      "current_price_usd": 0.0032144531877325412,
      "price_change_24h": 6.23,
      "tx_volume_u_24h": 426483.285599,
      "holders": 18786,
      "market_cap": "3214049.6570458425349641916730945372",
      "fdv": "3214049.6570458425349641916730945372",
      "risk_score": "55"
    },
    {
      "token": "2TK6MgLTmHDhmdh4EtdnBkYKZPkcjMp6cj3gcWhqpump",
      "chain": "solana",
      "symbol": "MMC",
      "name": "MMC",
      "logo_url": "https://www.iconaves.com/ipfs/pump/2TK6MgLTmHDhmdh4EtdnBkYKZPkcjMp6cj3gcWhqpump.png",
      "current_price_usd": 0.000825502189686293,
      "price_change_24h": 570.83,
      "tx_volume_u_24h": 421149.058076,
      "holders": 2089,
      "market_cap": "824548.922174902309256552510165",
      "fdv": "824548.922174902309256552510165",
      "risk_score": "40"
    },
    {
      "token": "4FkNq8RcCYg4ZGDWh14scJ7ej3m5vMjYTcWoJVkupump",
      "chain": "solana",
      "symbol": "LUMO",
      "name": "LUMO",
      "logo_url": "https://www.iconaves.com/ipfs/pump/4FkNq8RcCYg4ZGDWh14scJ7ej3m5vMjYTcWoJVkupump.png",
      "current_price_usd": 0.005174119903144214,
      "price_change_24h": -0.54,
      "tx_volume_u_24h": 415271.91512,
      "holders": 9418,
      "market_cap": "5174035.717075379256539510804852",
      "fdv": "5174035.717075379256539510804852",
      "risk_score": "40"
    },
    {
      "token": "4rwPNRSFgcS7EGphFdX7VwXuhjZGxph7gYyb7Zp2pump",
      "chain": "solana",
      "symbol": "AuraFarm",
      "name": "AuraFarm",
      "logo_url": "https://www.iconaves.com/ipfs/pump/4rwPNRSFgcS7EGphFdX7VwXuhjZGxph7gYyb7Zp2pump.png",
      "current_price_usd": 0.0024618277788047344,
      "price_change_24h": 1.58,
      "tx_volume_u_24h": 413628.17371,
      "holders": 3129,
      "market_cap": "2461204.221453244203520537574912",
      "fdv": "2461204.221453244203520537574912",
      "risk_score": "40"
    },
    {
      "token": "9DHe3pycTuymFk4H4bbPoAJ4hQrr2kaLDF6J6aAKpump",
      "chain": "solana",
      "symbol": "BUZZ",
      "name": "BUZZ",
      "logo_url": "https://www.iconaves.com/ipfs/pump/9DHe3pycTuymFk4H4bbPoAJ4hQrr2kaLDF6J6aAKpump.png",
      "current_price_usd": 0.006405765311959678,
      "price_change_24h": -1.34,
      "tx_volume_u_24h": 410336.348267,
      "holders": 29399,
      "market_cap": "6404865.669392631286515431324164",
      "fdv": "6404865.669392631286515431324164",
      "risk_score": "40"
    },
    {
      "token": "FkT2JJHDLL5eyBeeX7RjFevXSP5UDwRkiMCusg3ypump",
      "chain": "solana",
      "symbol": "URMOM",
      "name": "URMOM",
      "logo_url": "https://www.iconaves.com/ipfs/pump/FkT2JJHDLL5eyBeeX7RjFevXSP5UDwRkiMCusg3ypump_147.webp",
      "current_price_usd": 0.00012582014475536496,
      "price_change_24h": -46.76,
      "tx_volume_u_24h": 401055.878024,
      "holders": 1493,
      "market_cap": "125815.64062938762521634761673504",
      "fdv": "125815.64062938762521634761673504",
      "risk_score": "0"
    },
    {
      "token": "9jUb38tuMqsCe328tM7kxFEm3wRpbo3MbXPJoFiTpump",
      "chain": "solana",
      "symbol": "land",
      "name": "land",
      "logo_url": "https://www.iconaves.com/ipfs/pump/9jUb38tuMqsCe328tM7kxFEm3wRpbo3MbXPJoFiTpump.png",
      "current_price_usd": 0.0002634416606899458,
      "price_change_24h": -15.78,
      "tx_volume_u_24h": 395568.558177,
      "holders": 3761,
      "market_cap": "263426.8568594493803463274146822",
      "fdv": "263426.8568594493803463274146822",
      "risk_score": "0"
    },
    {
      "token": "qRUZaCpgxaRH1s5V6opjPA6Hnpv5BM37LqkDBw7pump",
      "chain": "solana",
      "symbol": "MvG",
      "name": "MvG",
      "logo_url": "https://www.iconaves.com/ipfs/pump/qRUZaCpgxaRH1s5V6opjPA6Hnpv5BM37LqkDBw7pump.png",
      "current_price_usd": 0.0002553425236303648,
      "price_change_24h": -23.27,
      "tx_volume_u_24h": 384184.24286,
      "holders": 5646,
      "market_cap": "255312.6026892132840529224700640",
      "fdv": "255312.6026892132840529224700640",
      "risk_score": "0"
    },
    {
      "token": "CSgLJ6wu9AoJGi4TpC31Lr5CCQkZbwkSUTW6REeC5K3J",
      "chain": "solana",
      "symbol": "LPC",
      "name": "LPC",
      "logo_url": "",
      "current_price_usd": 0.01767104761742846,
      "price_change_24h": 469.69,
      "tx_volume_u_24h": 378670.740807,
      "holders": 2070,
      "market_cap": "17620237.48887228950280282751582318",
      "fdv": "17620237.48887228950280282751582318",
      "risk_score": "40"
    },
    {
      "token": "y1AZt42vceCmStjW4zetK3VoNarC1VxJ5iDjpiupump",
      "chain": "solana",
      "symbol": "FARTBOY",
      "name": "FARTBOY",
      "logo_url": "https://www.iconaves.com/token_icon/solana/y1AZt42vceCmStjW4zetK3VoNarC1VxJ5iDjpiupump.png",
      "current_price_usd": 0.02493890099639392,
      "price_change_24h": -0.6,
      "tx_volume_u_24h": 375066.252081,
      "holders": 12410,
      "market_cap": "24924894.90536976379058197637462752",
      "fdv": "24924894.90536976379058197637462752",
      "risk_score": "40"
    },
    {
      "token": "4Cnk9EPnW5ixfLZatCPJjDB1PUtcRpVVgTQukm9epump",
      "chain": "solana",
      "symbol": "DADDY",
      "name": "DADDY",
      "logo_url": "https://www.iconaves.com/token_icon/solana/4Cnk9EPnW5ixfLZatCPJjDB1PUtcRpVVgTQukm9epump.png",
      "current_price_usd": 0.04206882943746939,
      "price_change_24h": 0.14,
      "tx_volume_u_24h": 372316.08235126646,
      "holders": 70831,
      "market_cap": "25226160.9172447457666329143945",
      "fdv": "25226160.9172447457666329143945",
      "risk_score": "40"
    },
    {
      "token": "DzvWsz4eLG2i2326E81rFxjTqaa476khgPRpRzrcpump",
      "chain": "solana",
      "symbol": "TNN",
      "name": "TNN",
      "logo_url": "https://www.iconaves.com/ipfs/pump/DzvWsz4eLG2i2326E81rFxjTqaa476khgPRpRzrcpump.png",
      "current_price_usd": 0.00014680637356740504,
      "price_change_24h": 58.03,
      "tx_volume_u_24h": 370596.121609,
      "holders": 1239,
      "market_cap": "146738.36509082160371543208531096",
      "fdv": "146738.36509082160371543208531096",
      "risk_score": "0"
    },
    {
      "token": "fRfKGCriduzDwSudCwpL7ySCEiboNuryhZDVJtr1a1C",
      "chain": "solana",
      "symbol": "DUPE",
      "name": "DUPE",
      "logo_url": "",
      "current_price_usd": 0.002431851002841634,
      "price_change_24h": -5.76,
      "tx_volume_u_24h": 370462.230541,
      "holders": 2258,
      "market_cap": "2431845.272150095810565037253589498",
      "fdv": "2431845.272150095810565037253589498",
      "risk_score": "55"
    },
    {
      "token": "ts3foLrNUMvwdVeit1oNeLWjYk7e4qsn8PqSsqRpump",
      "chain": "solana",
      "symbol": "ANTIRUG",
      "name": "ANTIRUG",
      "logo_url": "https://www.iconaves.com/ipfs/pump/ts3foLrNUMvwdVeit1oNeLWjYk7e4qsn8PqSsqRpump.png",
      "current_price_usd": 0.004058697327228797,
      "price_change_24h": 56.54,
      "tx_volume_u_24h": 360175.04446,
      "holders": 3878,
      "market_cap": "4057853.093270050525573251794973",
      "fdv": "4057853.093270050525573251794973",
      "risk_score": "40"
    },
    {
      "token": "14jazxRjHyaYsGoFk1u3CZSmgswYginbtTK8Z9PAboop",
      "chain": "solana",
      "symbol": "Dingo",
      "name": "Dingo",
      "logo_url": "https://www.iconaves.com/boop/solana/14jazxRjHyaYsGoFk1u3CZSmgswYginbtTK8Z9PAboop_147.webp",
      "current_price_usd": 0.0005478557496552231,
      "price_change_24h": 42.6,
      "tx_volume_u_24h": 356471.523888,
      "holders": 1618,
      "market_cap": "547841.3720291833014910497311568993",
      "fdv": "547841.3720291833014910497311568993",
      "risk_score": "40"
    },
    {
      "token": "CoRAitPvr9seu5F9Hk39vbjqA1o1XuoryHjSk1Z1q2mo",
      "chain": "solana",
      "symbol": "CORAL",
      "name": "CORAL",
      "logo_url": "",
      "current_price_usd": 0.0016149750575292182,
      "price_change_24h": 17.11,
      "tx_volume_u_24h": 356313.50949768,
      "holders": 1068,
      "market_cap": "16149750.5752921820000000000",
      "fdv": "16149750.5752921820000000000",
      "risk_score": "40"
    },
    {
      "token": "3S8qX1MsMqRbiwKg2cQyx7nis1oHMgaCuc9c4VfvVdPN",
      "chain": "solana",
      "symbol": "MOTHER",
      "name": "MOTHER",
      "logo_url": "https://www.iconaves.com/token_icon/solana/3S8qX1MsMqRbiwKg2cQyx7nis1oHMgaCuc9c4VfvVdPN_1737366225.png",
      "current_price_usd": 0.00888043446414127,
      "price_change_24h": -6.8,
      "tx_volume_u_24h": 354918.997943935,
      "holders": 27014,
      "market_cap": "8757278.55029834258728561720833",
      "fdv": "8757278.55029834258728561720833",
      "risk_score": "40"
    },
    {
      "token": "4TBi66vi32S7J8X1A6eWfaLHYmUXu7CStcEmsJQdpump",
      "chain": "solana",
      "symbol": "Ghibli",
      "name": "Ghibli",
      "logo_url": "https://www.logofacade.com/ipfs/pump/4TBi66vi32S7J8X1A6eWfaLHYmUXu7CStcEmsJQdpump.png",
      "current_price_usd": 0.0030711427243178555,
      "price_change_24h": -6.58,
      "tx_volume_u_24h": 353892.860693,
      "holders": 14958,
      "market_cap": "3070819.7333158110593596154303390",
      "fdv": "3070819.7333158110593596154303390",
      "risk_score": "40"
    },
    {
      "token": "BuNonfvszzm6dJuzigNbde7qGNmcSYxT64erw3Wboop",
      "chain": "solana",
      "symbol": "DeFi",
      "name": "DeFi",
      "logo_url": "https://www.iconaves.com/boop/solana/BuNonfvszzm6dJuzigNbde7qGNmcSYxT64erw3Wboop_147_20250505181153.webp",
      "current_price_usd": 0.00010339067609153998,
      "price_change_24h": -49.76,
      "tx_volume_u_24h": 350058.131537,
      "holders": 1429,
      "market_cap": "103390.67609153998000000000",
      "fdv": "103390.67609153998000000000",
      "risk_score": "40"
    },
    {
      "token": "9u8PP725K2GUf4p5bhKebrzHTGgvHp6KDeQPf7jc1F1W",
      "chain": "solana",
      "symbol": "POPE",
      "name": "POPE",
      "logo_url": "https://www.iconaves.com/token_icon/solana/9u8PP725K2GUf4p5bhKebrzHTGgvHp6KDeQPf7jc1F1W.png",
      "current_price_usd": 0.05352289032847927,
      "price_change_24h": 1.83,
      "tx_volume_u_24h": 331649.770846,
      "holders": 1931,
      "market_cap": "53522884.82125540203413824880333589",
      "fdv": "53522884.82125540203413824880333589",
      "risk_score": "55"
    },
    {
      "token": "FvgqHMfL9yn39V79huDPy3YUNDoYJpuLWng2JfmQpump",
      "chain": "solana",
      "symbol": "$URO",
      "name": "Urolithin A",
      "logo_url": "https://www.iconaves.com/token_icon/solana/FvgqHMfL9yn39V79huDPy3YUNDoYJpuLWng2JfmQpump.png",
      "current_price_usd": 0.002210978798335099,
      "price_change_24h": -18.89,
      "tx_volume_u_24h": 312273.24623,
      "holders": 17961,
      "market_cap": "2209938.226869689390714216922163",
      "fdv": "2209938.226869689390714216922163",
      "risk_score": "40"
    },
    {
      "token": "H4phNbsqjV5rqk8u6FUACTLB6rNZRTAPGnBb8KXJpump",
      "chain": "solana",
      "symbol": "SSE",
      "name": "SSE",
      "logo_url": "https://www.iconaves.com/token_icon/solana/H4phNbsqjV5rqk8u6FUACTLB6rNZRTAPGnBb8KXJpump.png",
      "current_price_usd": 0.005950036673994504,
      "price_change_24h": -3.8,
      "tx_volume_u_24h": 307949.131856,
      "holders": 17378,
      "market_cap": "5949881.504811328835195623882704",
      "fdv": "5949881.504811328835195623882704",
      "risk_score": "40"
    },
    {
      "token": "YAFAJvjUv9MVAKcTE7Y8ouo45QNKVK6fCMzdxt2tjPs",
      "chain": "solana",
      "symbol": "YAFA",
      "name": "YAFA",
      "logo_url": "https://www.iconaves.com/token_icon_solana/solana/YAFAJvjUv9MVAKcTE7Y8ouo45QNKVK6fCMzdxt2tjPs.png",
      "current_price_usd": 0.021507650220550307,
      "price_change_24h": -0.92,
      "tx_volume_u_24h": 305647.124256,
      "holders": 23251,
      "market_cap": "21507620.304553530374561091439154",
      "fdv": "21507620.304553530374561091439154",
      "risk_score": "40"
    },
    {
      "token": "BQQzEvYT4knThhkSPBvSKBLg1LEczisWLhx5ydJipump",
      "chain": "solana",
      "symbol": "Buckazoids",
      "name": "Buckazoids",
      "logo_url": "https://www.iconaves.com/ipfs/pump/BQQzEvYT4knThhkSPBvSKBLg1LEczisWLhx5ydJipump.png",
      "current_price_usd": 0.0028345305546635426,
      "price_change_24h": 5.96,
      "tx_volume_u_24h": 303229.486204,
      "holders": 11547,
      "market_cap": "2834295.1238668030096885903581850",
      "fdv": "2834295.1238668030096885903581850",
      "risk_score": "40"
    },
    {
      "token": "5d3kw2KR7hfaja214tL9hqYSxFSoq9uDF9GB7GKboop",
      "chain": "solana",
      "symbol": "FARM",
      "name": "FARM",
      "logo_url": "https://www.iconaves.com/boop/solana/5d3kw2KR7hfaja214tL9hqYSxFSoq9uDF9GB7GKboop_147.webp",
      "current_price_usd": 0.0006531763774751723,
      "price_change_24h": 23.85,
      "tx_volume_u_24h": 303060.442862,
      "holders": 1423,
      "market_cap": "653118.8492838058418499541249554152",
      "fdv": "653118.8492838058418499541249554152",
      "risk_score": "40"
    },
    {
      "token": "5LJMJyR8MtAkbtpf8kFUV7S9oFG3xaGDdcnFxYt9pump",
      "chain": "solana",
      "symbol": "FAT",
      "name": "FAT",
      "logo_url": "https://www.iconaves.com/ipfs/pump/5LJMJyR8MtAkbtpf8kFUV7S9oFG3xaGDdcnFxYt9pump.png",
      "current_price_usd": 0.004958445198195669,
      "price_change_24h": -4.32,
      "tx_volume_u_24h": 298115.192497,
      "holders": 13576,
      "market_cap": "4957927.607216358341869968369213",
      "fdv": "4957927.607216358341869968369213",
      "risk_score": "40"
    },
    {
      "token": "BQwYE9jDG8MmLNrTY82J8Lq63YGR6namdpBERckEpump",
      "chain": "solana",
      "symbol": "McTrump ",
      "name": "McTrump ",
      "logo_url": "https://www.iconaves.com/ipfs/pump/BQwYE9jDG8MmLNrTY82J8Lq63YGR6namdpBERckEpump.png",
      "current_price_usd": 0.00035146638507525883,
      "price_change_24h": 0.3,
      "tx_volume_u_24h": 294930.1852112096,
      "holders": 1548,
      "market_cap": "351384.9760002972247899320014827",
      "fdv": "351384.9760002972247899320014827",
      "risk_score": "40"
    },
    {
      "token": "GtDZKAqvMZMnti46ZewMiXCa4oXF4bZxwQPoKzXPFxZn",
      "chain": "solana",
      "symbol": "nub",
      "name": "nub",
      "logo_url": "https://www.iconaves.com/token_icon_solana/solana/GtDZKAqvMZMnti46ZewMiXCa4oXF4bZxwQPoKzXPFxZn.png",
      "current_price_usd": 0.00560226761312573,
      "price_change_24h": 2.17,
      "tx_volume_u_24h": 282467.168206,
      "holders": 21317,
      "market_cap": "5602007.33991181362773618180308424",
      "fdv": "5602007.33991181362773618180308424",
      "risk_score": "40"
    },
    {
      "token": "3yhsQKMeFDo3FN5vxRZnEvvr9cN67aU9qwrMrpURgHVU",
      "chain": "solana",
      "symbol": "DORA",
      "name": "DORA",
      "logo_url": "https://www.iconaves.com/token_icon_solana/solana/3yhsQKMeFDo3FN5vxRZnEvvr9cN67aU9qwrMrpURgHVU.png",
      "current_price_usd": 0.008770598011252038,
      "price_change_24h": 4.5,
      "tx_volume_u_24h": 278350.368501,
      "holders": 7849,
      "market_cap": "8760723.539862557772573972371022",
      "fdv": "8760723.539862557772573972371022",
      "risk_score": "40"
    },
    {
      "token": "8XtRWb4uAAJFMP4QQhoYYCWR6XXb7ybcCdiqPwz9s5WS",
      "chain": "solana",
      "symbol": "ALON",
      "name": "ALON",
      "logo_url": "",
      "current_price_usd": 0.005212734005272522,
      "price_change_24h": 22.18,
      "tx_volume_u_24h": 278256.743281,
      "holders": 16067,
      "market_cap": "5201963.901846991243537284675672",
      "fdv": "5201963.901846991243537284675672",
      "risk_score": "40"
    },
    {
      "token": "7BgBvyjrZX1YKz4oh9mjb8ZScatkkwb8DzFx7LoiVkM3",
      "chain": "solana",
      "symbol": "SLERF",
      "name": "SLERF",
      "logo_url": "https://www.iconaves.com/token_icon_request/6718fdbd9b841f4cb9c7997d_1729691070.png",
      "current_price_usd": 0.06764807447617976,
      "price_change_24h": 2.05,
      "tx_volume_u_24h": 276793.147929,
      "holders": 54727,
      "market_cap": "33823391.79645180610533050746777352",
      "fdv": "33823391.79645180610533050746777352",
      "risk_score": "40"
    },
    {
      "token": "5SVG3T9CNQsm2kEwzbRq6hASqh1oGfjqTtLXYUibpump",
      "chain": "solana",
      "symbol": "SIGMA",
      "name": "SIGMA",
      "logo_url": "https://www.iconaves.com/token_icon_solana/solana/5SVG3T9CNQsm2kEwzbRq6hASqh1oGfjqTtLXYUibpump.png",
      "current_price_usd": 0.018389357889854276,
      "price_change_24h": -3.23,
      "tx_volume_u_24h": 273881.143326,
      "holders": 28360,
      "market_cap": "16547217.814460490559340366245168",
      "fdv": "16547217.814460490559340366245168",
      "risk_score": "40"
    },
    {
      "token": "25hAyBQfoDhfWx9ay6rarbgvWGwDdNqcHsXS3jQ3mTDJ",
      "chain": "solana",
      "symbol": "MANEKI",
      "name": "MANEKI",
      "logo_url": "https://www.iconaves.com/token_icon_solana/solana/25hAyBQfoDhfWx9ay6rarbgvWGwDdNqcHsXS3jQ3mTDJ.png",
      "current_price_usd": 0.0016527618568411317,
      "price_change_24h": 1.14,
      "tx_volume_u_24h": 271945.870989,
      "holders": 70555,
      "market_cap": "14641340.446283997949425949811085",
      "fdv": "14641340.446283997949425949811085",
      "risk_score": "40"
    },
    {
      "token": "Aq8Gocyvyyi8xk5EYxd6viUfVmVvs9T9R6mZFzZFpump",
      "chain": "solana",
      "symbol": "HYPER",
      "name": "HYPER",
      "logo_url": "",
      "current_price_usd": 0.013970925452333771,
      "price_change_24h": 6.07,
      "tx_volume_u_24h": 271467.022767,
      "holders": 2152,
      "market_cap": "13932596.315755374397738830915417",
      "fdv": "13932596.315755374397738830915417",
      "risk_score": "40"
    },
    {
      "token": "VaxZxmFXV8tmsd72hUn22ex6GFzZ5uq9DVJ5wA5pump",
      "chain": "solana",
      "symbol": "OIIAOIIA",
      "name": "OIIAOIIA",
      "logo_url": "https://www.iconaves.com/token_icon_solana/solana/VaxZxmFXV8tmsd72hUn22ex6GFzZ5uq9DVJ5wA5pump.png",
      "current_price_usd": 0.005277267574149492,
      "price_change_24h": 9.53,
      "tx_volume_u_24h": 269718.173373,
      "holders": 6665,
      "market_cap": "5276311.509450106517094180785736",
      "fdv": "5276311.509450106517094180785736",
      "risk_score": "40"
    },
    {
      "token": "CQvadZTR8vikRqqwyhvYV8YpdfCRjUCGyQwCuY4rxBQt",
      "chain": "solana",
      "symbol": "Conan",
      "name": "Conan",
      "logo_url": "https://www.iconaves.com/token_icon_request/67931f66ee12d3567985b134_1737695078.png",
      "current_price_usd": 0.007590324107837595,
      "price_change_24h": -7.62,
      "tx_volume_u_24h": 268819.584411,
      "holders": 13443,
      "market_cap": "6245222.973727057047091464303840",
      "fdv": "6245222.973727057047091464303840",
      "risk_score": "20"
    },
    {
      "token": "CboMcTUYUcy9E6B3yGdFn6aEsGUnYV6yWeoeukw6pump",
      "chain": "solana",
      "symbol": "Butthole",
      "name": "Butthole",
      "logo_url": "https://www.iconaves.com/ipfs/pump/CboMcTUYUcy9E6B3yGdFn6aEsGUnYV6yWeoeukw6pump.png",
      "current_price_usd": 0.006401641412405621,
      "price_change_24h": -7.15,
      "tx_volume_u_24h": 266584.902442,
      "holders": 33440,
      "market_cap": "6401455.420526274562033362278195",
      "fdv": "6401455.420526274562033362278195",
      "risk_score": "40"
    },
    {
      "token": "6EXW1uMsNWX9e69Apw6DfFgnX3cc1AWjsQo75zDepump",
      "chain": "solana",
      "symbol": "LockedIn",
      "name": "LockedIn",
      "logo_url": "https://www.iconaves.com/ipfs/pump/6EXW1uMsNWX9e69Apw6DfFgnX3cc1AWjsQo75zDepump_147.webp",
      "current_price_usd": 0.0002217513816788636,
      "price_change_24h": -8.33,
      "tx_volume_u_24h": 265763.462126,
      "holders": 2648,
      "market_cap": "221729.2371568146389721120601340",
      "fdv": "221729.2371568146389721120601340",
      "risk_score": "0"
    },
    {
      "token": "hU3Rpq6U57KjNGSQmembpsK71ic6VkKayy7HQEgBoNk",
      "chain": "solana",
      "symbol": "BEERCOIN",
      "name": "BEERCOIN",
      "logo_url": "https://www.iconaves.com/ipfs/bonk/hU3Rpq6U57KjNGSQmembpsK71ic6VkKayy7HQEgBoNk_147_20250506080635.webp",
      "current_price_usd": 0.00027559916286501554,
      "price_change_24h": -28.72,
      "tx_volume_u_24h": 265355.29338073713,
      "holders": 1264,
      "market_cap": "275599.16286501554000000000",
      "fdv": "275599.16286501554000000000",
      "risk_score": "40"
    },
    {
      "token": "9XjiBXqM8yKk345CMtrWsfoVeXvGZxk1xZD4bdTEbTcv",
      "chain": "solana",
      "symbol": "RICHIE",
      "name": "RICHIE",
      "logo_url": "",
      "current_price_usd": 0.050195854002944275,
      "price_change_24h": 26.76,
      "tx_volume_u_24h": 256220.537405,
      "holders": 1300,
      "market_cap": "1194961.777451208364965981662362950",
      "fdv": "1505875.620088328250000000",
      "risk_score": "55"
    },
    {
      "token": "4b9f8SeEhKSSEJz9NtZQTqPc2ap2wRk8ZvdKU2zAqX1s",
      "chain": "solana",
      "symbol": "MRB",
      "name": "MRB",
      "logo_url": "",
      "current_price_usd": 0.001161333725833436,
      "price_change_24h": 3.48,
      "tx_volume_u_24h": 255609.53956331333,
      "holders": 1955,
      "market_cap": "116133.372583343600000000",
      "fdv": "116133.372583343600000000",
      "risk_score": "40"
    },
    {
      "token": "ZEUS1aR7aX8DFFJf5QjWj2ftDDdNTroMNGo8YoQm3Gq",
      "chain": "solana",
      "symbol": "ZEUS",
      "name": "ZEUS",
      "logo_url": "https://www.iconaves.com/token_icon_solana/solana/ZEUS1aR7aX8DFFJf5QjWj2ftDDdNTroMNGo8YoQm3Gq.png",
      "current_price_usd": 0.24187272544279237,
      "price_change_24h": 1,
      "tx_volume_u_24h": 253328.621639,
      "holders": 90561,
      "market_cap": "241872049.5789144175607553629702",
      "fdv": "241872049.5789144175607553629702",
      "risk_score": "55"
    },
    {
      "token": "Cmt6QFnpJnQDJuY7bE3ThaMDvaExPmoSHfEJE8BDpump",
      "chain": "solana",
      "symbol": "POPE",
      "name": "POPE",
      "logo_url": "https://www.iconaves.com/ipfs/pump/Cmt6QFnpJnQDJuY7bE3ThaMDvaExPmoSHfEJE8BDpump.png",
      "current_price_usd": 0.00027434751320878323,
      "price_change_24h": -0.94,
      "tx_volume_u_24h": 243485.244196,
      "holders": 1198,
      "market_cap": "274271.7023371345470986374004454",
      "fdv": "274271.7023371345470986374004454",
      "risk_score": "40"
    },
    {
      "token": "dog1viwbb2vWDpER5FrJ4YFG6gq6XuyFohUe9TXN65u",
      "chain": "solana",
      "symbol": "DOG",
      "name": "DOG",
      "logo_url": "",
      "current_price_usd": 0.0028526867352007086,
      "price_change_24h": 3.08,
      "tx_volume_u_24h": 241337.12541651708,
      "holders": 4026,
      "market_cap": "285268614.238748823300414233073330",
      "fdv": "285268614.238748823300414233073330",
      "risk_score": "55"
    },
    {
      "token": "7XJiwLDrjzxDYdZipnJXzpr1iDTmK55XixSFAa7JgNEL",
      "chain": "solana",
      "symbol": "MLG",
      "name": "MLG",
      "logo_url": "https://www.iconaves.com/token_icon_solana/solana/7XJiwLDrjzxDYdZipnJXzpr1iDTmK55XixSFAa7JgNEL.png",
      "current_price_usd": 0.003978680389955516,
      "price_change_24h": -14.84,
      "tx_volume_u_24h": 237792.232034,
      "holders": 27108,
      "market_cap": "3968834.919651893826044341092128",
      "fdv": "3968834.919651893826044341092128",
      "risk_score": "40"
    },
    {
      "token": "C9FVTtx4WxgHmz55FEvQgykq8rqiLS8xRBVgqQVtpump",
      "chain": "solana",
      "symbol": "CENTS",
      "name": "CENTS",
      "logo_url": "https://www.iconaves.com/token_icon_solana/solana/C9FVTtx4WxgHmz55FEvQgykq8rqiLS8xRBVgqQVtpump.png",
      "current_price_usd": 0.0003798772402992692,
      "price_change_24h": 26.73,
      "tx_volume_u_24h": 236151.417068,
      "holders": 12987,
      "market_cap": "379832.69785055345840693416076",
      "fdv": "379832.69785055345840693416076",
      "risk_score": "40"
    },
    {
      "token": "7oLWGMuGbBm9uwDmffSdxLE98YChFAH1UdY5XpKYLff8",
      "chain": "solana",
      "symbol": "WOJAK",
      "name": "WOJAK",
      "logo_url": "",
      "current_price_usd": 0.0007755841424825426,
      "price_change_24h": 41.66,
      "tx_volume_u_24h": 233598.0617508194,
      "holders": 1131,
      "market_cap": "694802.9626162387737809483169858",
      "fdv": "694802.9626162387737809483169858",
      "risk_score": "40"
    },
    {
      "token": "AxGAbdFtdbj2oNXa4dKqFvwHzgFtW9mFHWmd7vQfpump",
      "chain": "solana",
      "symbol": "HAT",
      "name": "HAT",
      "logo_url": "https://www.iconaves.com/token_icon_solana/solana/AxGAbdFtdbj2oNXa4dKqFvwHzgFtW9mFHWmd7vQfpump.png",
      "current_price_usd": 0.0033376304469101507,
      "price_change_24h": -2.29,
      "tx_volume_u_24h": 232430.81242374313,
      "holders": 14628,
      "market_cap": "3304238.5476679522323427431488024",
      "fdv": "3304238.5476679522323427431488024",
      "risk_score": "40"
    },
    {
      "token": "FVdo7CDJarhYoH6McyTFqx71EtzCPViinvdd1v86Qmy5",
      "chain": "solana",
      "symbol": "Aimonica",
      "name": "Aimonica",
      "logo_url": "https://www.iconaves.com/token_icon_solana/solana/FVdo7CDJarhYoH6McyTFqx71EtzCPViinvdd1v86Qmy5.png",
      "current_price_usd": 0.005442849398405954,
      "price_change_24h": -6.87,
      "tx_volume_u_24h": 230840.887687,
      "holders": 35008,
      "market_cap": "5442589.073941336723121816770962",
      "fdv": "5442589.073941336723121816770962",
      "risk_score": "40"
    },
    {
      "token": "ATRLuHph8dxnPny4WSNW7fxkhbeivBrtWbY6BfB4xpLj",
      "chain": "solana",
      "symbol": "ATR",
      "name": "ATR",
      "logo_url": "https://www.iconaves.com/token_icon/solana/ATRLuHph8dxnPny4WSNW7fxkhbeivBrtWbY6BfB4xpLj.png",
      "current_price_usd": 0.0211816895537921,
      "price_change_24h": 3.73,
      "tx_volume_u_24h": 229724.339805,
      "holders": 12401,
      "market_cap": "26768599.2053187146097741175819159",
      "fdv": "26768599.2053187146097741175819159",
      "risk_score": "55"
    },
    {
      "token": "GkeUTuaFB4oZADaqiCo3yauHNx9SxUNn8euHptEEbonk",
      "chain": "solana",
      "symbol": "Grassito",
      "name": "Grassito",
      "logo_url": "https://www.iconaves.com/ipfs/bonk/GkeUTuaFB4oZADaqiCo3yauHNx9SxUNn8euHptEEbonk.png",
      "current_price_usd": 4.5214115861510097e-7,
      "price_change_24h": -41.57,
      "tx_volume_u_24h": 227625.993229,
      "holders": 5027,
      "market_cap": "187820.29799403032525169354440939361",
      "fdv": "187820.29799403032525169354440939361",
      "risk_score": "40"
    },
    {
      "token": "UbCSotjZpnDYrFk8vydbJWxYEuoJiSptyujPojApump",
      "chain": "solana",
      "symbol": "asscoin",
      "name": "asscoin",
      "logo_url": "https://www.iconaves.com/ipfs/pump/UbCSotjZpnDYrFk8vydbJWxYEuoJiSptyujPojApump.png",
      "current_price_usd": 0.0004341064185658247,
      "price_change_24h": 39.44,
      "tx_volume_u_24h": 224580.701552,
      "holders": 3184,
      "market_cap": "433645.2234988231553985529383263",
      "fdv": "433645.2234988231553985529383263",
      "risk_score": "40"
    },
    {
      "token": "9gyfbPVwwZx4y1hotNSLcqXCQNpNqqz6ZRvo8yTLpump",
      "chain": "solana",
      "symbol": "YZY",
      "name": "YZY",
      "logo_url": "https://www.iconaves.com/ipfs/pump/9gyfbPVwwZx4y1hotNSLcqXCQNpNqqz6ZRvo8yTLpump.png",
      "current_price_usd": 0.0026092320676159653,
      "price_change_24h": -1.26,
      "tx_volume_u_24h": 220445.429617,
      "holders": 10919,
      "market_cap": "2607981.6940215288216505779639465",
      "fdv": "2607981.6940215288216505779639465",
      "risk_score": "40"
    },
    {
      "token": "AsyfR3e5JcPqWot4H5MMhQUm7DZ4zwQrcp2zbB7vpump",
      "chain": "solana",
      "symbol": "IQ",
      "name": "IQ",
      "logo_url": "https://www.iconaves.com/token_icon_solana/solana/AsyfR3e5JcPqWot4H5MMhQUm7DZ4zwQrcp2zbB7vpump.png",
      "current_price_usd": 0.0026771062556854436,
      "price_change_24h": 38.11,
      "tx_volume_u_24h": 218891.83205975365,
      "holders": 7474,
      "market_cap": "2674683.7770999055895618539593972",
      "fdv": "2674683.7770999055895618539593972",
      "risk_score": "40"
    },
    {
      "token": "212fTsxhWnBmNjyYSSLo61ox9VDRfFnLxc6VcNMRpump",
      "chain": "solana",
      "symbol": "Vanta",
      "name": "Vanta",
      "logo_url": "https://www.iconaves.com/ipfs/pump/212fTsxhWnBmNjyYSSLo61ox9VDRfFnLxc6VcNMRpump_147.webp",
      "current_price_usd": 0.000047058068914599934,
      "price_change_24h": -62.37,
      "tx_volume_u_24h": 217247.780326,
      "holders": 1217,
      "market_cap": "47058.068914599934000000000",
      "fdv": "47058.068914599934000000000",
      "risk_score": "0"
    },
    {
      "token": "R6Res6qfWxgDGom5CpUEvxt7DNJu62bWvbgj7Vkboop",
      "chain": "solana",
      "symbol": "PORK",
      "name": "PORK",
      "logo_url": "https://www.iconaves.com/boop/solana/R6Res6qfWxgDGom5CpUEvxt7DNJu62bWvbgj7Vkboop_147_20250504201500.webp",
      "current_price_usd": 0.00022131563646811804,
      "price_change_24h": -46.54,
      "tx_volume_u_24h": 216756.163229,
      "holders": 2593,
      "market_cap": "221313.29409520448196128146703877652",
      "fdv": "221313.29409520448196128146703877652",
      "risk_score": "40"
    },
    {
      "token": "HBoNJ5v8g71s2boRivrHnfSB5MVPLDHHyVjruPfhGkvL",
      "chain": "solana",
      "symbol": "PURPE",
      "name": "PURPE",
      "logo_url": "https://www.iconaves.com/token_icon_solana/solana/HBoNJ5v8g71s2boRivrHnfSB5MVPLDHHyVjruPfhGkvL_20240710100945.png",
      "current_price_usd": 0.000052892462715313434,
      "price_change_24h": -7.79,
      "tx_volume_u_24h": 213406.589255,
      "holders": 46522,
      "market_cap": "22250634.5031608563842899037546",
      "fdv": "22250634.5031608563842899037546",
      "risk_score": "40"
    },
    {
      "token": "nosXBVoaCTtYdLvKY6Csb4AC8JCdQKKAaWYtx2ZMoo7",
      "chain": "solana",
      "symbol": "NOS",
      "name": "NOS",
      "logo_url": "https://www.iconaves.com/token_icon/solana/nosXBVoaCTtYdLvKY6Csb4AC8JCdQKKAaWYtx2ZMoo7.png",
      "current_price_usd": 0.746503412650324,
      "price_change_24h": -3.54,
      "tx_volume_u_24h": 210768.870306,
      "holders": 48578,
      "market_cap": "74650273.145035057022083172516",
      "fdv": "74650273.145035057022083172516",
      "risk_score": "50"
    }
  ],
  "timestamp": 1746661164835
}